{"recommendations": [{"rating": null, "alg_json": "{\"recall\":\"cf_TUUT\",\"name\":\"no_stype\",\"stype\":\"None\"}", "sharing_url": "https://movie.douban.com/subject/35925201/", "title": "\u4f0a\u85e4\u6da6\u4e8c\u72c2\u70ed\uff1a\u65e5\u672c\u6050\u6016\u6545\u4e8b", "url": "https://movie.douban.com/subject/35925201/", "pic": {"large": "https://img1.doubanio.com/view/photo/m_ratio_poster/public/p2881821098.webp", "normal": "https://img1.doubanio.com/view/photo/s_ratio_poster/public/p2881821098.webp"}, "uri": "douban://douban.com/tv/35925201", "interest": null, "type": "tv", "id": "35925201"}, {"rating": null, "alg_json": "{\"recall\":\"cf_TUUT\",\"name\":\"no_stype\",\"stype\":\"None\"}", "sharing_url": "https://movie.douban.com/subject/35785946/", "title": "\u5c3c\u5c14\uff1a\u673a\u68b0\u7eaa\u5143 \u52a8\u753b\u7248", "url": "https://movie.douban.com/subject/35785946/", "pic": {"large": "https://img1.doubanio.com/view/photo/m_ratio_poster/public/p2880847310.webp", "normal": "https://img1.doubanio.com/view/photo/s_ratio_poster/public/p2880847310.webp"}, "uri": "douban://douban.com/tv/35785946", "interest": null, "type": "tv", "id": "35785946"}, {"rating": {"count": 54273, "max": 10, "star_count": 4.5, "value": 8.5}, "alg_json": "{\"recall\":\"cf_TUUT\",\"name\":\"no_stype\",\"stype\":\"None\"}", "sharing_url": "https://movie.douban.com/subject/35284242/", "title": "\u75af\u72c2\u52a8\u7269\u57ce+", "url": "https://movie.douban.com/subject/35284242/", "pic": {"large": "https://img2.doubanio.com/view/photo/m_ratio_poster/public/p2883556682.webp", "normal": "https://img2.doubanio.com/view/photo/s_ratio_poster/public/p2883556682.webp"}, "uri": "douban://douban.com/tv/35284242", "interest": null, "type": "tv", "id": "35284242"}, {"rating": null, "alg_json": "{\"recall\":\"cf_TUUT\",\"name\":\"no_stype\",\"stype\":\"None\"}", "sharing_url": "https://movie.douban.com/subject/36056894/", "title": "\u7231\uff0c\u6b7b\u4ea1\u548c\u673a\u5668\u4eba \u7b2c\u56db\u5b63", "url": "https://movie.douban.com/subject/36056894/", "pic": {"large": "https://img1.doubanio.com/view/photo/m_ratio_poster/public/p2877782729.webp", "normal": "https://img1.doubanio.com/view/photo/s_ratio_poster/public/p2877782729.webp"}, "uri": "douban://douban.com/tv/36056894", "interest": null, "type": "tv", "id": "36056894"}, {"rating": {"count": 400, "max": 10, "star_count": 4.0, "value": 7.5}, "alg_json": "{\"recall\":\"cf_TUUT\",\"name\":\"no_stype\",\"stype\":\"None\"}", "sharing_url": "https://movie.douban.com/subject/35235187/", "title": "\u8f7b\u677e\u5c0f\u718a\uff1a\u4e3b\u9898\u4e50\u56ed\u5927\u5192\u9669", "url": "https://movie.douban.com/subject/35235187/", "pic": {"large": "https://img1.doubanio.com/view/photo/m_ratio_poster/public/p2876473549.webp", "normal": "https://img1.doubanio.com/view/photo/s_ratio_poster/public/p2876473549.webp"}, "uri": "douban://douban.com/tv/35235187", "interest": null, "type": "tv", "id": "35235187"}, {"rating": {"count": 36180, "max": 10, "star_count": 4.5, "value": 8.8}, "alg_json": "{\"recall\":\"cf_TUUT\",\"name\":\"no_stype\",\"stype\":\"None\"}", "sharing_url": "https://movie.douban.com/subject/35256195/", "title": "\u7535\u952f\u4eba", "url": "https://movie.douban.com/subject/35256195/", "pic": {"large": "https://img1.doubanio.com/view/photo/m_ratio_poster/public/p2876941907.webp", "normal": "https://img1.doubanio.com/view/photo/s_ratio_poster/public/p2876941907.webp"}, "uri": "douban://douban.com/tv/35256195", "interest": null, "type": "tv", "id": "35256195"}, {"rating": null, "alg_json": "{\"recall\":\"cf_TUUT\",\"name\":\"no_stype\",\"stype\":\"None\"}", "sharing_url": "https://movie.douban.com/subject/35337634/", "title": "\u5730\u72f1\u4e50", "url": "https://movie.douban.com/subject/35337634/", "pic": {"large": "https://img1.doubanio.com/view/photo/m_ratio_poster/public/p2789542198.webp", "normal": "https://img1.doubanio.com/view/photo/s_ratio_poster/public/p2789542198.webp"}, "uri": "douban://douban.com/tv/35337634", "interest": null, "type": "tv", "id": "35337634"}, {"rating": {"count": 129519, "max": 10, "star_count": 4.5, "value": 8.9}, "alg_json": "{\"recall\":\"cf_TUUT\",\"name\":\"no_stype\",\"stype\":\"None\"}", "sharing_url": "https://movie.douban.com/subject/35258427/", "title": "\u95f4\u8c0d\u8fc7\u5bb6\u5bb6", "url": "https://movie.douban.com/subject/35258427/", "pic": {"large": "https://img1.doubanio.com/view/photo/m_ratio_poster/public/p2869306649.webp", "normal": "https://img1.doubanio.com/view/photo/s_ratio_poster/public/p2869306649.webp"}, "uri": "douban://douban.com/tv/35258427", "interest": null, "type": "tv", "id": "35258427"}, {"rating": {"count": 716, "max": 10, "star_count": 4.0, "value": 8.2}, "alg_json": "{\"recall\":\"cf_TUUT\",\"name\":\"no_stype\",\"stype\":\"None\"}", "sharing_url": "https://movie.douban.com/subject/34896436/", "title": "\u9b3c\u65cf\uff1a\u96f7\u795e\u4f20\u8bf4", "url": "https://movie.douban.com/subject/34896436/", "pic": {"large": "https://img2.doubanio.com/view/photo/m_ratio_poster/public/p2881726051.webp", "normal": "https://img2.doubanio.com/view/photo/s_ratio_poster/public/p2881726051.webp"}, "uri": "douban://douban.com/tv/34896436", "interest": null, "type": "tv", "id": "34896436"}, {"rating": {"count": 250, "max": 10, "star_count": 4.5, "value": 8.9}, "alg_json": "{\"recall\":\"cf_TUUT\",\"name\":\"no_stype\",\"stype\":\"None\"}", "sharing_url": "https://movie.douban.com/subject/35919126/", "title": "\u5929\u7afa\u9f20\u8f66\u8f66 \u5b66\u8f66\u7bc7", "url": "https://movie.douban.com/subject/35919126/", "pic": {"large": "https://img2.doubanio.com/view/photo/m_ratio_poster/public/p2880864163.webp", "normal": "https://img2.doubanio.com/view/photo/s_ratio_poster/public/p2880864163.webp"}, "uri": "douban://douban.com/tv/35919126", "interest": null, "type": "tv", "id": "35919126"}, {"rating": {"count": 12119, "max": 10, "star_count": 4.5, "value": 9.3}, "alg_json": "{\"recall\":\"cf_TUUT\",\"name\":\"no_stype\",\"stype\":\"None\"}", "sharing_url": "https://movie.douban.com/subject/35314507/", "title": "\u5929\u7afa\u9f20\u8f66\u8f66", "url": "https://movie.douban.com/subject/35314507/", "pic": {"large": "https://img1.doubanio.com/view/photo/m_ratio_poster/public/p2629954180.webp", "normal": "https://img1.doubanio.com/view/photo/s_ratio_poster/public/p2629954180.webp"}, "uri": "douban://douban.com/tv/35314507", "interest": null, "type": "tv", "id": "35314507"}, {"rating": {"count": 4417, "max": 10, "star_count": 4.5, "value": 9.0}, "alg_json": "{\"recall\":\"cf_TUUT\",\"name\":\"no_stype\",\"stype\":\"None\"}", "sharing_url": "https://movie.douban.com/subject/35563505/", "title": "\u56db\u53e0\u534a\u65f6\u5149\u673a", "url": "https://movie.douban.com/subject/35563505/", "pic": {"large": "https://img2.doubanio.com/view/photo/m_ratio_poster/public/p2876841181.webp", "normal": "https://img2.doubanio.com/view/photo/s_ratio_poster/public/p2876841181.webp"}, "uri": "douban://douban.com/tv/35563505", "interest": null, "type": "tv", "id": "35563505"}, {"rating": {"count": 15542, "max": 10, "star_count": 4.5, "value": 9.1}, "alg_json": "{\"recall\":\"cf_TUUT\",\"name\":\"no_stype\",\"stype\":\"None\"}", "sharing_url": "https://movie.douban.com/subject/35724582/", "title": "\u95f4\u8c0d\u8fc7\u5bb6\u5bb6 Part 2", "url": "https://movie.douban.com/subject/35724582/", "pic": {"large": "https://img1.doubanio.com/view/photo/m_ratio_poster/public/p2878984749.webp", "normal": "https://img1.doubanio.com/view/photo/s_ratio_poster/public/p2878984749.webp"}, "uri": "douban://douban.com/tv/35724582", "interest": null, "type": "tv", "id": "35724582"}, {"rating": null, "alg_json": "{\"recall\":\"cf_TUUT\",\"name\":\"no_stype\",\"stype\":\"None\"}", "sharing_url": "https://movie.douban.com/subject/35765350/", "title": "\u5492\u672f\u56de\u6218 \u7b2c\u4e8c\u5b63", "url": "https://movie.douban.com/subject/35765350/", "pic": {"large": "https://img2.doubanio.com/view/photo/m_ratio_poster/public/p2880471573.webp", "normal": "https://img2.doubanio.com/view/photo/s_ratio_poster/public/p2880471573.webp"}, "uri": "douban://douban.com/tv/35765350", "interest": null, "type": "tv", "id": "35765350"}, {"rating": {"count": 554, "max": 10, "star_count": 4.5, "value": 8.8}, "alg_json": "{\"recall\":\"cf_TUUT\",\"name\":\"no_stype\",\"stype\":\"None\"}", "sharing_url": "https://movie.douban.com/subject/35882524/", "title": "\u5173\u4e8e\u517b\u732b\u6211\u4e00\u76f4\u662f\u65b0\u624b", "url": "https://movie.douban.com/subject/35882524/", "pic": {"large": "https://img9.doubanio.com/view/photo/m_ratio_poster/public/p2875331625.webp", "normal": "https://img9.doubanio.com/view/photo/s_ratio_poster/public/p2875331625.webp"}, "uri": "douban://douban.com/tv/35882524", "interest": null, "type": "tv", "id": "35882524"}, {"rating": {"count": 11836, "max": 10, "star_count": 4.0, "value": 8.3}, "alg_json": "{\"recall\":\"cf_TUUT\",\"name\":\"no_stype\",\"stype\":\"None\"}", "sharing_url": "https://movie.douban.com/subject/35284240/", "title": "\u5927\u767d\uff01", "url": "https://movie.douban.com/subject/35284240/", "pic": {"large": "https://img2.doubanio.com/view/photo/m_ratio_poster/public/p2875376963.webp", "normal": "https://img2.doubanio.com/view/photo/s_ratio_poster/public/p2875376963.webp"}, "uri": "douban://douban.com/tv/35284240", "interest": null, "type": "tv", "id": "35284240"}, {"rating": {"count": 3363, "max": 10, "star_count": 4.5, "value": 8.9}, "alg_json": "{\"recall\":\"cf_TUUT\",\"name\":\"no_stype\",\"stype\":\"None\"}", "sharing_url": "https://movie.douban.com/subject/35617459/", "title": "\u540d\u4fa6\u63a2\u67ef\u5357\uff1a\u72af\u4eba\u72af\u6cfd\u5148\u751f", "url": "https://movie.douban.com/subject/35617459/", "pic": {"large": "https://img1.doubanio.com/view/photo/m_ratio_poster/public/p2876426158.webp", "normal": "https://img1.doubanio.com/view/photo/s_ratio_poster/public/p2876426158.webp"}, "uri": "douban://douban.com/tv/35617459", "interest": null, "type": "tv", "id": "35617459"}, {"rating": null, "alg_json": "{\"recall\":\"cf_TUUT\",\"name\":\"no_stype\",\"stype\":\"None\"}", "sharing_url": "https://movie.douban.com/subject/35745547/", "title": "\u5927\u96ea\u6d77\u7684\u51ef\u7eb3", "url": "https://movie.douban.com/subject/35745547/", "pic": {"large": "https://img1.doubanio.com/view/photo/m_ratio_poster/public/p2884179280.webp", "normal": "https://img1.doubanio.com/view/photo/s_ratio_poster/public/p2884179280.webp"}, "uri": "douban://douban.com/tv/35745547", "interest": null, "type": "tv", "id": "35745547"}, {"rating": {"count": 482, "max": 10, "star_count": 3.0, "value": 6.3}, "alg_json": "{\"recall\":\"cf_TUUT\",\"name\":\"no_stype\",\"stype\":\"None\"}", "sharing_url": "https://movie.douban.com/subject/35497962/", "title": "\u4f8b\u5916", "url": "https://movie.douban.com/subject/35497962/", "pic": {"large": "https://img1.doubanio.com/view/photo/m_ratio_poster/public/p2881805199.webp", "normal": "https://img1.doubanio.com/view/photo/s_ratio_poster/public/p2881805199.webp"}, "uri": "douban://douban.com/tv/35497962", "interest": null, "type": "tv", "id": "35497962"}, {"rating": {"count": 606, "max": 10, "star_count": 4.5, "value": 8.7}, "alg_json": "{\"recall\":\"cf_TUUT\",\"name\":\"no_stype\",\"stype\":\"None\"}", "sharing_url": "https://movie.douban.com/subject/35417778/", "title": "\u624b\u5de5\u5c11\u5973\uff01", "url": "https://movie.douban.com/subject/35417778/", "pic": {"large": "https://img1.doubanio.com/view/photo/m_ratio_poster/public/p2878242777.webp", "normal": "https://img1.doubanio.com/view/photo/s_ratio_poster/public/p2878242777.webp"}, "uri": "douban://douban.com/tv/35417778", "interest": null, "type": "tv", "id": "35417778"}], "movie_info": {"id": "35927178", "title": "\u86cb\u9ec4\u54e5\u5927\u5192\u9669", "original_title": "\u3050\u3067\u305f\u307e \u301c\u6bcd\u3092\u305f\u305a\u306d\u3066\u3069\u3093\u304f\u3089\u3044\u301c", "year": "2022", "is_tv": true, "rating": null, "poster": "https://img9.doubanio.com/view/photo/m_ratio_poster/public/p2882746866.webp"}}