[{"original_price": null, "rating": {"count": 295622, "max": 10, "value": 7.7, "star_count": 4.0}, "actions": [], "is_new_tv": false, "year": "2022", "card_subtitle": "2022 / \u4e2d\u56fd\u5927\u9646 / \u5947\u5e7b \u53e4\u88c5 / \u4f0a\u5ce5 \u94b1\u656c\u5348 / \u865e\u4e66\u6b23 \u738b\u9e64\u68e3", "recommend_comment": "\u76ee\u524d\u4e0d\u60f3\u548c\u6ca1\u770b\u8fc7\u82cd\u5170\u8bc0\u7684\u4eba\u8bf4\u8bdd \u2014\u2014 \u76d0\u7c92\u7c92\u7684\u77ed\u8bc4", "id": "34779776", "title": "\u82cd\u5170\u8bc0", "label": null, "actors": ["\u865e\u4e66\u6b23", "\u738b\u9e64\u68e3", "\u5f90\u6d77\u4e54"], "interest": null, "type": "tv", "description": "", "has_linewatch": true, "price": null, "date": null, "info": "\u4e2d\u56fd\u5927\u9646 / \u5947\u5e7b \u53e4\u88c5 / \u4f0a\u5ce5 / \u865e\u4e66\u6b23 \u738b\u9e64\u68e3", "url": "https://movie.douban.com/subject/34779776/", "release_date": "08.07", "cover": {"url": "https://img9.doubanio.com/view/photo/m_ratio_poster/public/p2674132194.jpg", "width": 3750, "shape": "rectangle", "height": 6667}, "uri": "douban://douban.com/tv/34779776", "episodes_info": "\u66f4\u65b0\u81f330\u96c6", "subtype": "", "directors": ["\u4f0a\u5ce5"], "reviewer_name": "", "null_rating_reason": ""}, {"original_price": null, "rating": {"count": 357827, "max": 10, "value": 5.8, "star_count": 3.0}, "actions": [], "is_new_tv": false, "year": "2022", "card_subtitle": "2022 / \u4e2d\u56fd\u5927\u9646 / \u53e4\u88c5 / \u90ed\u864e \u4efb\u6d77\u6d9b / \u6768\u7d2b \u6210\u6bc5", "recommend_comment": "\u672c\u4ed9\u5076\u7231\u597d\u8005\u770b\u8fc7\u4e09\u751f\u82b1\u5343\u9aa8\u9999\u871c\u7409\u7483\u5343\u53e4\u7b49\u4e00\u5806\u3002\u3002\u3002\u73b0\u5728\u6c89\u9999\u770b\u5230\u7b2c\u4e94\u96c6\u4e86\u3002\u3002\u3002\u771f\u7684\u89c9\u5f97\u8fd9\u662f\u770b\u8fc7\u6700\u6ca1\u4ed9\u5473\u7684\u4e00\u90e8\u3002\u3002\u3002\n\n\u4f60\u80fd\u60f3\u5230\u4ed9\u4f8d\u7684\u96f6\u5634\u662f\u5543\u9ec4\u74dc\u3002\u3002\u3002\n\n\u5e1d\u541b\u4ed9\u4eba\u4eec\u8fd8\u8981\u6709\u4e13\u95e8\u7684\u5bab\u6bbf\u6bcf\u65e5\u505a\u996d\u3002\u3002\u3002\n\n\u5973\u4e3b\u60f3\u5077\u8d70\u7537\u4e3b\u7684\u8863\u670d\u8ba9\u4ed6\u6ca1\u8863\u670d\u7a7f\u3002\u3002\u3002\n\n\u5e1d\u541b\u4e0b\u754c\u8c08\u5224\u8fd8\u8981\u5148\u6536\u62fe\u884c\u56ca\u3002\u3002\u3002\n\n\u62dc\u6258\u4f60\u4eec\u4e0d\u662f\u4ed9\u4eba\u5417\u3002\u3002\u3002\u4e0d\u5e94\u8be5\u4e0d\u600e\u4e48\u9700\u8981\u8fdb\u98df\u5417\u3002\u3002\u3002\u4e0d\u5e94\u8be5\u4e00\u6325\u624b\u8fd9\u4e9b\u4e1c\u897f\u5c31\u51fa\u73b0\u4e86\u5417 \u2014\u2014 \u65e0\u804a\u554a\u554a\uff08\u91cd\u751f\u7684\u77ed\u8bc4", "id": "35029547", "title": "\u6c89\u9999\u5982\u5c51\u00b7\u6c89\u9999\u91cd\u534e", "label": null, "actors": ["\u6768\u7d2b", "\u6210\u6bc5", "\u5f20\u777f"], "interest": null, "type": "tv", "description": "", "has_linewatch": true, "price": null, "date": null, "info": "\u4e2d\u56fd\u5927\u9646 / \u53e4\u88c5 / \u90ed\u864e / \u6768\u7d2b \u6210\u6bc5", "url": "https://movie.douban.com/subject/35029547/", "release_date": "07.20", "cover": {"url": "https://img9.doubanio.com/view/photo/m_ratio_poster/public/p2876528670.jpg", "width": 2000, "shape": "rectangle", "height": 3555}, "uri": "douban://douban.com/tv/35029547", "episodes_info": "\u66f4\u65b0\u81f345\u96c6", "subtype": "", "directors": ["\u90ed\u864e"], "reviewer_name": "", "null_rating_reason": ""}, {"original_price": null, "rating": {"count": 352867, "max": 10, "value": 7.6, "star_count": 4.0}, "actions": [], "is_new_tv": false, "year": "2022", "card_subtitle": "2022 / \u4e2d\u56fd\u5927\u9646 / \u5267\u60c5 \u7231\u60c5 / \u8d39\u632f\u7fd4 / \u5434\u78ca \u8d75\u9732\u601d", "recommend_comment": "\u5bb6\u5b85\u641e\u7b11\u9017\u4e50\u65e5\u5e38\u2260\u9e21\u72ac\u4e0d\u5b81\u4e0a\u8e7f\u4e0b\u8df3\uff0c\u641e\u7b11\u62c5\u5f53\u2260\u52a8\u4f5c\u6d6e\u5938\u4e94\u5b98\u4e71\u98de\uff0c\u5bfc\u6f14\u8fd9\u603c\u8138\u955c\u5934\u628a\u4eba\u62cd\u5f97\u4e11\u7edd\uff0c\u6211\u7684\u8bc4\u4ef7\u662f\u4e0d\u5982\u67d0\u7a7a\u955c\u4e4b\u738b\u3002\u7a0b\u5bb6\u620f\u4efd\u770b\u5f97\u4eba\u811a\u8dbe\u6293\u5730\u53ea\u60f3\u5feb\u8fdb\u3002\u4e3b\u6f14\u4e5f\u6ca1\u5565cp\u611f\uff0c\u9732\u601d\u867d\u7136\u4e00\u76f4\u8425\u9500\u751c\u59b9\uff0c\u4f46\u5979\u6709\u4e00\u79cd\u6f2b\u4e0d\u7ecf\u5fc3\u540a\u513f\u90ce\u5f53\u7684\u6c14\u8d28\uff0c\u548c\u5434\u78ca\u4e0d\u9002\u914d\u3002\u78ca\u548c\u5979\u7ad9\u5728\u4e00\u8d77\u5e74\u4e0b\u611f\u592a\u660e\u663e\u4e86\uff0c\u5f88\u4e0d\u642d\u3002 \u2014\u2014 momo\u7684\u77ed\u8bc4", "id": "35452438", "title": "\u661f\u6c49\u707f\u70c2\u00b7\u6708\u5347\u6ca7\u6d77", "label": null, "actors": ["\u5434\u78ca", "\u8d75\u9732\u601d", "\u90ed\u6d9b"], "interest": null, "type": "tv", "description": "", "has_linewatch": true, "price": null, "date": null, "info": "\u4e2d\u56fd\u5927\u9646 / \u5267\u60c5 \u7231\u60c5 / \u8d39\u632f\u7fd4 / \u5434\u78ca \u8d75\u9732\u601d", "url": "https://movie.douban.com/subject/35452438/", "release_date": "07.05", "cover": {"url": "https://img9.doubanio.com/view/photo/m_ratio_poster/public/p2875643522.jpg", "width": 3001, "shape": "rectangle", "height": 4500}, "uri": "douban://douban.com/tv/35452438", "episodes_info": "\u66f4\u65b0\u81f346\u96c6", "subtype": "", "directors": ["\u8d39\u632f\u7fd4"], "reviewer_name": "", "null_rating_reason": ""}, {"original_price": null, "rating": {"count": 742043, "max": 10, "value": 8.0, "star_count": 4.0}, "actions": [], "is_new_tv": false, "year": "2022", "card_subtitle": "2022 / \u4e2d\u56fd\u5927\u9646 / \u5267\u60c5 \u7231\u60c5 \u53e4\u88c5 / \u6768\u9633 / \u5218\u4ea6\u83f2 \u9648\u6653", "recommend_comment": "\u5218\u4ea6\u83f2\u4e5f\u592a\u7f8e\u4e86 \u2014\u2014 \u5728\u9003\u83e0\u841d\u7684\u77ed\u8bc4", "id": "35231822", "title": "\u68a6\u534e\u5f55", "label": null, "actors": ["\u5218\u4ea6\u83f2", "\u9648\u6653", "\u67f3\u5ca9"], "interest": null, "type": "tv", "description": "", "has_linewatch": true, "price": null, "date": null, "info": "\u4e2d\u56fd\u5927\u9646 / \u5267\u60c5 \u7231\u60c5 \u53e4\u88c5 / \u6768\u9633 / \u5218\u4ea6\u83f2 \u9648\u6653", "url": "https://movie.douban.com/subject/35231822/", "release_date": "06.02", "cover": {"url": "https://img9.doubanio.com/view/photo/m_ratio_poster/public/p2656327176.jpg", "width": 2000, "shape": "rectangle", "height": 3540}, "uri": "douban://douban.com/tv/35231822", "episodes_info": "", "subtype": "", "directors": ["\u6768\u9633"], "reviewer_name": "", "null_rating_reason": ""}, {"original_price": null, "rating": null, "actions": [], "is_new_tv": false, "year": "2022", "card_subtitle": "2022 / \u4e2d\u56fd\u5927\u9646 / \u5267\u60c5 \u72af\u7f6a / \u5085\u4e1c\u80b2 / \u9648\u6653 \u738b\u4e00\u535a", "recommend_comment": "\u6211\u5bb6\u91cc\u6709\u8b66\u5bdf\uff0c\u6240\u4ee5\u5bf9\u8fd9\u79cd\u9898\u6750\u5929\u7136\u597d\u611f\uff0c\u4e5f\u5929\u7136\u6311\u5254\u3002\u4f46\u662f\u4eca\u5929\u770b\u4e86\u51e0\u96c6\uff0c\u80fd\u611f\u89c9\u5230\u5236\u4f5c\u65b9\u975e\u5e38\u7528\u5fc3\uff0c\u5f88\u591a\u4e13\u4e1a\u672f\u8bed\u90fd\u6ca1\u6bdb\u75c5\u3002\u6211\u518d\u4e3e\u4e2a\u4f8b\u5b50\uff0c\u8b66\u5bdf\u56e0\u4e3a\u53d7\u8bad\u8fc7\uff0c\u8d70\u8def\u59ff\u52bf\u5176\u5b9e\u90fd\u6709\u7279\u70b9\uff0c\u8fd9\u4e2a\u6ca1\u60f3\u5230\u4e3b\u6f14\u4e5f\u505a\u5230\u4e86\uff0c\u5f88\u63d0\u5347\u597d\u611f\uff01\u738b\u4e00\u535a\u7528\u5fc3\u4e86\uff0c\u6f14\u7684\u4e0d\u9519\u3002 \u2014\u2014 \u98de\u884c\u666e\u7538\u7684\u77ed\u8bc4", "id": "34908108", "title": "\u51b0\u96e8\u706b", "label": null, "actors": ["\u9648\u6653", "\u738b\u4e00\u535a", "\u738b\u52b2\u677e"], "interest": null, "type": "tv", "description": "", "has_linewatch": true, "price": null, "date": null, "info": "\u4e2d\u56fd\u5927\u9646 / \u5267\u60c5 \u72af\u7f6a / \u5085\u4e1c\u80b2 / \u9648\u6653 \u738b\u4e00\u535a", "url": "https://movie.douban.com/subject/34908108/", "release_date": "08.11", "cover": {"url": "https://img9.doubanio.com/view/photo/m_ratio_poster/public/p2877710972.jpg", "width": 3072, "shape": "rectangle", "height": 4803}, "uri": "douban://douban.com/tv/34908108", "episodes_info": "\u66f4\u65b0\u81f315\u96c6", "subtype": "", "directors": ["\u5085\u4e1c\u80b2"], "reviewer_name": "", "null_rating_reason": "\u6682\u65e0\u8bc4\u5206"}, {"original_price": null, "rating": {"count": 7281, "max": 10, "value": 8.7, "star_count": 4.5}, "actions": [], "is_new_tv": false, "year": "2022", "card_subtitle": "2022 / \u7f8e\u56fd / \u5267\u60c5 \u52a8\u4f5c \u7231\u60c5 / \u7c73\u683c\u5c14\u00b7\u8428\u666e\u4ec0\u5c3c\u514b \u514b\u83b1\u5c14\u00b7\u57fa\u5c14\u7eb3 \u683c\u5854\u00b7\u5e15\u7279\u5c14 \u683c\u96f7\u683c\u00b7\u827e\u5766\u5c3c\u65af / \u5e15\u8fea\u00b7\u5eb7\u65af\u6234\u6069 \u9a6c\u7279\u00b7\u53f2\u5bc6\u65af", "recommend_comment": "\u5973\u4e3b\u600e\u4e48\u957f\u5f97\u548c\u9648\u51ef\u6b4c\u4e00\u6837\uff1f\uff01 \u2014\u2014 \u4e00\u52fa\u54a9\u54a9\u7684\u77ed\u8bc4", "id": "34825964", "title": "\u9f99\u4e4b\u5bb6\u65cf", "label": null, "actors": ["\u5e15\u8fea\u00b7\u5eb7\u65af\u6234\u6069", "\u9a6c\u7279\u00b7\u53f2\u5bc6\u65af", "\u7c73\u8389\u00b7\u963f\u5c14\u67ef\u514b"], "interest": null, "type": "tv", "description": "", "has_linewatch": false, "price": null, "date": null, "info": "\u7f8e\u56fd / \u5267\u60c5 \u52a8\u4f5c \u7231\u60c5 / \u7c73\u683c\u5c14\u00b7\u8428\u666e\u4ec0\u5c3c\u514b / \u5e15\u8fea\u00b7\u5eb7\u65af\u6234\u6069 \u9a6c\u7279\u00b7\u53f2\u5bc6\u65af", "url": "https://movie.douban.com/subject/34825964/", "release_date": "08.21", "cover": {"url": "https://img9.doubanio.com/view/photo/m_ratio_poster/public/p2874976551.jpg", "width": 4050, "shape": "rectangle", "height": 6000}, "uri": "douban://douban.com/tv/34825964", "episodes_info": "", "subtype": "", "directors": ["\u7c73\u683c\u5c14\u00b7\u8428\u666e\u4ec0\u5c3c\u514b"], "reviewer_name": "", "null_rating_reason": ""}, {"original_price": null, "rating": {"count": 70458, "max": 10, "value": 9.0, "star_count": 4.5}, "actions": [], "is_new_tv": false, "year": "2022", "card_subtitle": "2022 / \u97e9\u56fd / \u5267\u60c5 \u559c\u5267 / \u5218\u4ec1\u503c / \u6734\u6069\u658c \u59dc\u6cf0\u4f0d", "recommend_comment": "\u4e00\u4e2a\u8fde\u4ec0\u4e48\u662f\u6b7b\u90fd\u4e0d\u61c2\u7684\u50bb\u74dc\uff0c\u5374\u751f\u6015\u6211\u4f1a\u6b7b\uff0c\u8fd9\u7adf\u6210\u4e3a\u4e86\u6211\u7684\u5b89\u6170\u3002 \u2014\u2014 \u5f53\u5f53\u5f53\u5f53\u7684\u77ed\u8bc4", "id": "35524446", "title": "\u975e\u5e38\u5f8b\u5e08\u79b9\u82f1\u7991", "label": null, "actors": ["\u6734\u6069\u658c", "\u59dc\u6cf0\u4f0d", "\u59dc\u5176\u6c38"], "interest": null, "type": "tv", "description": "", "has_linewatch": false, "price": null, "date": null, "info": "\u97e9\u56fd / \u5267\u60c5 \u559c\u5267 / \u5218\u4ec1\u503c / \u6734\u6069\u658c \u59dc\u6cf0\u4f0d", "url": "https://movie.douban.com/subject/35524446/", "release_date": "06.29", "cover": {"url": "https://img9.doubanio.com/view/photo/m_ratio_poster/public/p2873967682.jpg", "width": 1200, "shape": "rectangle", "height": 1719}, "uri": "douban://douban.com/tv/35524446", "episodes_info": "", "subtype": "", "directors": ["\u5218\u4ec1\u503c"], "reviewer_name": "", "null_rating_reason": ""}, {"original_price": null, "rating": {"count": 49110, "max": 10, "value": 6.6, "star_count": 3.5}, "actions": [], "is_new_tv": false, "year": "2022", "card_subtitle": "2022 / \u4e2d\u56fd\u5927\u9646 / \u5267\u60c5 \u559c\u5267 \u7231\u60c5 / \u674e\u5c11\u98de / \u5f20\u5609\u76ca \u95eb\u59ae", "recommend_comment": "\u201c\u5988\u7ed9\u4f60\u627e\u4e86\u4e00\u4e2a\u5173\u7cfb\uff0c\u53ef\u4ee5\u8ba9\u4f60\u76f4\u63a5\u8fdb\u56fd\u5bb6\u8bdd\u5267\u9662\u201d\u54c8\u54c8\u54c8\u54c8\u54c8\u7f16\u5267\u8df3\u9884\u8a00\u5bb6\u5566 \u2014\u2014 \u7518\u9732\u5bfa\u94c1T\u83ab\u8a00\u7684\u77ed\u8bc4", "id": "35048530", "title": "\u5c11\u5e74\u6d3e2", "label": null, "actors": ["\u5f20\u5609\u76ca", "\u95eb\u59ae", "\u8d75\u4eca\u9ea6"], "interest": null, "type": "tv", "description": "", "has_linewatch": true, "price": null, "date": null, "info": "\u4e2d\u56fd\u5927\u9646 / \u5267\u60c5 \u559c\u5267 \u7231\u60c5 / \u674e\u5c11\u98de / \u5f20\u5609\u76ca \u95eb\u59ae", "url": "https://movie.douban.com/subject/35048530/", "release_date": "07.21", "cover": {"url": "https://img9.doubanio.com/view/photo/m_ratio_poster/public/p2867195596.jpg", "width": 2215, "shape": "rectangle", "height": 3101}, "uri": "douban://douban.com/tv/35048530", "episodes_info": "40\u96c6\u5168", "subtype": "", "directors": ["\u674e\u5c11\u98de"], "reviewer_name": "", "null_rating_reason": ""}, {"original_price": null, "rating": {"count": 20917, "max": 10, "value": 4.8, "star_count": 2.5}, "actions": [], "is_new_tv": false, "year": "2022", "card_subtitle": "2022 / \u4e2d\u56fd\u5927\u9646 / \u5267\u60c5 \u7231\u60c5 / \u7b80\u5ddd\u8a38 / \u6c5f\u758f\u5f71 \u6768\u91c7\u94b0", "recommend_comment": "\u5f88\u4e0d\u751f\u6d3b\u5316\u554a\u3002\u611f\u89c9\u90fd\u7aef\u7740\uff0c\u50cf\u4e0a\u4e00\u5b63\u7684\u5b89\u8fea\uff0c\u6211\u597d\u50cf\u518d\u770b\u5b89\u8fea\u548c\u5b89\u8fea\u5728\u6f14\u620f\u3002 \u2014\u2014 \u4e0d\u662fmayu\u662f\u9ebb\u53cb\u7684\u77ed\u8bc4", "id": "26779426", "title": "\u6b22\u4e50\u98823", "label": null, "actors": ["\u6c5f\u758f\u5f71", "\u6768\u91c7\u94b0", "\u5f20\u4f73\u5b81"], "interest": null, "type": "tv", "description": "", "has_linewatch": true, "price": null, "date": null, "info": "\u4e2d\u56fd\u5927\u9646 / \u5267\u60c5 \u7231\u60c5 / \u7b80\u5ddd\u8a38 / \u6c5f\u758f\u5f71 \u6768\u91c7\u94b0", "url": "https://movie.douban.com/subject/26779426/", "release_date": "08.11", "cover": {"url": "https://img9.doubanio.com/view/photo/m_ratio_poster/public/p2877695818.jpg", "width": 3000, "shape": "rectangle", "height": 5333}, "uri": "douban://douban.com/tv/26779426", "episodes_info": "\u66f4\u65b0\u81f322\u96c6", "subtype": "", "directors": ["\u7b80\u5ddd\u8a38"], "reviewer_name": "", "null_rating_reason": ""}, {"original_price": null, "rating": null, "actions": [], "is_new_tv": false, "year": "2022", "card_subtitle": "2022 / \u4e2d\u56fd\u5927\u9646 / \u5267\u60c5 \u7231\u60c5 / \u9ece\u5fd7 / \u5173\u6653\u5f64 \u535c\u51a0\u4eca", "recommend_comment": "25\u5c81\u3002\u4e00\u4e2a\u559c\u63d0\u4e00\u8f86\u8f66\uff0c\u4e00\u4e2a\u5f00\u4e00\u5bb6\u516c\u53f8\uff0c\u4e00\u4e2a\u540d\u5217\u524d\u8305\u7f51\u7ea2\u4e3b\u64ad\uff0c\u4e00\u4e2a\u6295\u884c\u7cbe\u82f1\u3002\u8fd9\u3002\u3002\u3002\u800c\u4e14\u611f\u89c9\u5267\u60c5\u53f0\u8bcd\u6f14\u6280\u548c\u7b2c\u4e00\u5b63\u6bd4\u90fd\u5dee \u2014\u2014 \u5e55\u53f6\u4e0b\u7684\u77ed\u8bc4", "id": "35203351", "title": "\u4e8c\u5341\u4e0d\u60d12", "label": null, "actors": ["\u5173\u6653\u5f64", "\u535c\u51a0\u4eca", "\u8463\u601d\u6021"], "interest": null, "type": "tv", "description": "", "has_linewatch": true, "price": null, "date": null, "info": "\u4e2d\u56fd\u5927\u9646 / \u5267\u60c5 \u7231\u60c5 / \u9ece\u5fd7 / \u5173\u6653\u5f64 \u535c\u51a0\u4eca", "url": "https://movie.douban.com/subject/35203351/", "release_date": "08.17", "cover": {"url": "https://img9.doubanio.com/view/photo/m_ratio_poster/public/p2877690173.jpg", "width": 5906, "shape": "rectangle", "height": 10498}, "uri": "douban://douban.com/tv/35203351", "episodes_info": "\u66f4\u65b0\u81f316\u96c6", "subtype": "", "directors": ["\u9ece\u5fd7"], "reviewer_name": "", "null_rating_reason": "\u6682\u65e0\u8bc4\u5206"}, {"original_price": null, "rating": {"count": 81947, "max": 10, "value": 7.3, "star_count": 3.5}, "actions": [], "is_new_tv": false, "year": "2022", "card_subtitle": "2022 / \u4e2d\u56fd\u5927\u9646 / \u5267\u60c5 \u7231\u60c5 / \u6c88\u4e25 / \u96f7\u4f73\u97f3 \u5f20\u5b50\u67ab", "recommend_comment": "\u5982\u679c\u6ca1\u770b\u8fc7\u5c0f\u8bf4\u7684\u8bdd\uff0c\u5267\u8fd8\u7b97\u53ef\u4ee5\u3002\u4f46\u662f\u6709\u5c0f\u8bf4\u6253\u5e95\uff0c\u518d\u770b\u5bfc\u6f14\u7684\u6539\u7f16\uff0c\u5c31\u770b\u51fa\u4e86\u5bfc\u6f14\u7684\u5ba1\u7f8e\u662f\u591a\u4e48\u4f4e\u4e0b\u3002\u539f\u8457\u65e0\u5904\u4e0d\u5728\u51f8\u663e\u667a\u6167\u4e4b\u7f8e\uff0c\u6797\u671d\u5915\u6c89\u9759\u575a\u6bc5\u3001\u6b65\u6b65\u4e3a\u8425\uff0c\u6240\u4ee5\u624d\u80fd\u6210\u5c31\u540e\u6765\u6f2b\u957f\u7684\u5b66\u4e60\u4e4b\u8def\u3002\u5267\u5b8c\u5168\u843d\u5165\u4e86\u4e00\u822c\u7a7f\u8d8a\u5267\u7684\u4fd7\u5957\uff0c\u5973\u4e3b\u8fdb\u5165\u5f02\u4e16\u754c\u540e\u7684\u6240\u4f5c\u6240\u4e3a\u60c5\u7eea\u5316\u53c8\u65e0\u903b\u8f91\uff0c\u628a\u81ea\u5df1\u7a7f\u8d8a\u7684\u4e8b\u60c5\u5230\u5904\u8bf4\uff0c\u751f\u6015\u522b\u4eba\u4e0d\u77e5\u9053\u81ea\u5df1\u662f\u4e2a\u75af\u5b50\uff1f\u539f\u8457\u4ee5\u6210\u5e74\u4eba\u7684\u773c\u5149\u53bb\u770b\u5c0f\u5b66\u751f\u6d3b\uff0c\u672c\u6765\u5c31\u5f88\u6709\u8da3\uff0c\u4f46\u5bfc\u6f14\u5374\u6ca1\u6709\u80fd\u529b\u62cd\u51fa\u8fd9\u79cd\u8da3\u5473\u6027\uff0c\u53ea\u80fd\u7528\u8fd9\u79cd\u548b\u548b\u547c\u547c\u7684\u95f9\u5267\u6765\u63d0\u5347\u53ef\u770b\u5ea6\u3002\u800c\u82b1\u5377\u7a81\u7136\u664b\u5347\u7537\u4e8c\uff0c\u620f\u4efd\u5927\u5e45\u63d0\u5347\u4e0d\u8bf4\uff0c\u5168\u7a0b\u7adf\u7136\u662f\u4f5c\u4e3a\u538b\u5236\u5973\u4e3b\u7684\u667a\u6167\u62c5\u5f53\uff0c\u5728\u5bfc\u6f14\u7684\u5fc3\u76ee\u4e2d\u662f\u4e2a\u7537\u7684\u5c31\u5f97\u538b\u5973\u4e3b\u4e00\u5934\u662f\u5427\uff1f\u539f\u672c\u6211\u662f\u771f\u7684\u5f88\u559c\u6b22\u51e0\u4f4d\u4e3b\u6f14\uff0c\u5305\u62ec\u513f\u7ae5\u7248\uff0c\u5373\u4fbf\u5916\u5f62\u4e0a\u4e0d\u592a\u7b26\u5408\uff0c\u4f46\u4e5f\u76f8\u4fe1\u4ee5\u4ed6\u4eec\u7684\u6f14\u6280\u5b8c\u5168\u6709\u80fd\u529b\u5851\u9020\u51fa\u7b26\u5408\u539f\u8457\u7684\u5f62\u8c61\uff0c\u4f46\u5bfc\u6f14\u771f\u662f\u6f14\u5458\u7684\u4e0a\u9650\uff0c\u6f14\u5458\u9009\u5408\u4f5c\u56e2\u961f\u771f\u7684\u5f88\u91cd\u8981\u3002 \u2014\u2014 \u7ba1\u57cb\u5458\u7684\u77ed\u8bc4", "id": "34982236", "title": "\u5929\u624d\u57fa\u672c\u6cd5", "label": null, "actors": ["\u96f7\u4f73\u97f3", "\u5f20\u5b50\u67ab", "\u5f20\u65b0\u6210"], "interest": null, "type": "tv", "description": "", "has_linewatch": true, "price": null, "date": null, "info": "\u4e2d\u56fd\u5927\u9646 / \u5267\u60c5 \u7231\u60c5 / \u6c88\u4e25 / \u96f7\u4f73\u97f3 \u5f20\u5b50\u67ab", "url": "https://movie.douban.com/subject/34982236/", "release_date": "07.22", "cover": {"url": "https://img9.doubanio.com/view/photo/m_ratio_poster/public/p2876345437.jpg", "width": 1125, "shape": "rectangle", "height": 2000}, "uri": "douban://douban.com/tv/34982236", "episodes_info": "34\u96c6\u5168", "subtype": "", "directors": ["\u6c88\u4e25"], "reviewer_name": "", "null_rating_reason": ""}, {"original_price": null, "rating": {"count": 13941, "max": 10, "value": 5.0, "star_count": 2.5}, "actions": [], "is_new_tv": false, "year": "2022", "card_subtitle": "2022 / \u4e2d\u56fd\u5927\u9646 / \u5267\u60c5 / \u5b59\u7693 / \u8881\u6cc9 \u9ec4\u6653\u660e", "recommend_comment": "\u5929\u8fd8\u4eae\u7740\u5462\u5f8b\u6240\u5c31\u90fd\u4e0b\u73ed\u4e86 \u795e\u8bdd\u6545\u4e8b\u5427\u2026 \u2014\u2014 momo\u7684\u77ed\u8bc4", "id": "35396390", "title": "\u73ab\u7470\u4e4b\u6218", "label": null, "actors": ["\u8881\u6cc9", "\u9ec4\u6653\u660e", "\u4fde\u98de\u9e3f"], "interest": null, "type": "tv", "description": "", "has_linewatch": true, "price": null, "date": null, "info": "\u4e2d\u56fd\u5927\u9646 / \u5267\u60c5 / \u5b59\u7693 / \u8881\u6cc9 \u9ec4\u6653\u660e", "url": "https://movie.douban.com/subject/35396390/", "release_date": "08.08", "cover": {"url": "https://img9.doubanio.com/view/photo/m_ratio_poster/public/p2877141134.jpg", "width": 3652, "shape": "rectangle", "height": 6000}, "uri": "douban://douban.com/tv/35396390", "episodes_info": "\u66f4\u65b0\u81f336\u96c6", "subtype": "", "directors": ["\u5b59\u7693"], "reviewer_name": "", "null_rating_reason": ""}, {"original_price": null, "rating": {"count": 9741, "max": 10, "value": 6.1, "star_count": 3.0}, "actions": [], "is_new_tv": false, "year": "2022", "card_subtitle": "2022 / \u4e2d\u56fd\u5927\u9646 / \u5267\u60c5 \u60ac\u7591 / \u5f20\u4f1f\u514b / \u80e1\u4e00\u5929 \u5f20\u4e91\u9f99", "recommend_comment": "3.5\ud83c\udf1f\u5b9e\u5728\u65e0\u804a\u5230\u6ca1\u6709\u5267\u770b\u7684\u63a8\u7406\u7231\u597d\u8005\u53ef\u4ee5\u770b\uff0c\u6bd5\u7adf\u662f\u7ffb\u62cd\u6ce2\u6d1b\uff0c\u5267\u60c5\u600e\u4e48\u6298\u817e\u90fd\u4e0d\u4f1a\u79bb\u8c31\u3002\u4f46\u662f\u6b63\u662f\u56e0\u4e3a\u7ffb\u62cd\u6ce2\u6d1b\uff0c\u6ce2\u6d1b\u7684\u90a3\u79cd\u82f1\u5f0f\u5e7d\u9ed8\u4e3a\u4ec0\u4e48\u5728\u7537\u4e3b\u8fd9\u91cc\u5c31\u6210\u4e86\u975e\u5e38\u6b63\u6d3e\u7684\u75b2\u60eb\u611f\uff1f\u8def\u579a\u548c\u4e54\u695a\u751f\u51fa\u5f69\u662f\u56e0\u4e3a\u8fd9\u4e24\u4e2a\u4eba\u90fd\u6709\u8da3\uff0c\u4f46\u662f\u76ee\u524d\u770b\u4e54\u695a\u751f\u4eba\u8bbe\u6ca1\u600e\u4e48\u53d8\uff0c\u4f46\u662f\u8def\u579a\u5374\u53d8\u5f97\u5782\u5782\u8001\u77e3\u2026\u2026\u5176\u6b21\uff0c\u8fd9\u5267\u7684\u8282\u594f\u8fd8\u662f\u5982\u4e0a\u4e00\u90e8\u4e00\u6837\u2026\u2026 \u2014\u2014 \u6211\u4eec\u6709\u987e\u51c6\u7684\u77ed\u8bc4", "id": "35559680", "title": "\u6c11\u56fd\u5927\u4fa6\u63a2", "label": null, "actors": ["\u80e1\u4e00\u5929", "\u5f20\u4e91\u9f99", "\u5f20\u99a8\u4e88"], "interest": null, "type": "tv", "description": "", "has_linewatch": true, "price": null, "date": null, "info": "\u4e2d\u56fd\u5927\u9646 / \u5267\u60c5 \u60ac\u7591 / \u5f20\u4f1f\u514b / \u80e1\u4e00\u5929 \u5f20\u4e91\u9f99", "url": "https://movie.douban.com/subject/35559680/", "release_date": "08.10", "cover": {"url": "https://img9.doubanio.com/view/photo/m_ratio_poster/public/p2877632604.jpg", "width": 1247, "shape": "rectangle", "height": 2216}, "uri": "douban://douban.com/tv/35559680", "episodes_info": "24\u96c6\u5168", "subtype": "", "directors": ["\u5f20\u4f1f\u514b"], "reviewer_name": "", "null_rating_reason": ""}, {"original_price": null, "rating": {"count": 20077, "max": 10, "value": 8.4, "star_count": 4.0}, "actions": [], "is_new_tv": false, "year": "2022", "card_subtitle": "2022 / \u97e9\u56fd / \u5267\u60c5 \u72af\u7f6a \u60ac\u7591 / \u5434\u5e86\u7115 / \u674e\u949f\u7855 \u6797\u5141\u513f", "recommend_comment": "\u500d\u901f\u770b\u5b8c\uff0c\u65e0\u804a\u2026\u2026\u8fd8\u662f\u65e0\u804a\uff0c\u611f\u89c9\u8fde\u8c46\u63b0\u7684\u5267\u96c6\u7b80\u4ecb\u90fd\u6bd4\u6b63\u7247\u597d\u770b\u3002\uff08\u8fd9\u90fd\u80fd\u5f00\u52068.5\uff1f\u5567\u5567\u5567\uff0c\u8c46\u63b0\u2026\u2026\uff09 \u2014\u2014 \u522b\u4e86\uff0c\u602f\u61e6\u5c11\u5e74\u7684\u77ed\u8bc4", "id": "35465741", "title": "\u9ed1\u8bdd\u5f8b\u5e08", "label": null, "actors": ["\u674e\u949f\u7855", "\u6797\u5141\u513f", "\u91d1\u5468\u5baa"], "interest": null, "type": "tv", "description": "", "has_linewatch": false, "price": null, "date": null, "info": "\u97e9\u56fd / \u5267\u60c5 \u72af\u7f6a \u60ac\u7591 / \u5434\u5e86\u7115 / \u674e\u949f\u7855 \u6797\u5141\u513f", "url": "https://movie.douban.com/subject/35465741/", "release_date": "07.29", "cover": {"url": "https://img9.doubanio.com/view/photo/m_ratio_poster/public/p2876084495.jpg", "width": 1274, "shape": "rectangle", "height": 1800}, "uri": "douban://douban.com/tv/35465741", "episodes_info": "", "subtype": "", "directors": ["\u5434\u5e86\u7115"], "reviewer_name": "", "null_rating_reason": ""}, {"original_price": null, "rating": {"count": 206773, "max": 10, "value": 7.1, "star_count": 3.5}, "actions": [], "is_new_tv": false, "year": "2022", "card_subtitle": "2022 / \u4e2d\u56fd\u5927\u9646 / \u5267\u60c5 / \u90d1\u6653\u9f99 \u5218\u96ea\u677e \u59da\u8fdc / \u8d75\u4e3d\u9896 \u7f57\u664b", "recommend_comment": "\u770b\u4e86\u7b2c1-2\u96c6\uff0c2\u5206\u662f\u7ed9\u7f16\u5267\u7684\u3002\u4e66\u8bb0\u4e00\u5bb6\u4e0d\u7b97\u771f\u6b63\u610f\u4e49\u4e0a\u7684\u201c\u574f\u4eba\u201d\uff0c\u5e78\u798f\u50cf\u521d\u4e2d\u751f\uff0c\u5bf9\u5c31\u662f\uff0c\u9519\u5c31\u662f\u9519\uff0c\u50cf\u6781\u4e86\u6ca1\u6709\u63a5\u53d7\u8fc7\u793e\u4f1a\u6bd2\u6253\u7684\u5b66\u751f\u3002\u4e66\u8bb0\u4e00\u5bb6\u7ed9\u4e86\u53f0\u9636\uff0c\u6751\u91cc\u53c8\u8981\u4ef0\u4ed7\u4e66\u8bb0\u4e00\u5bb6\uff0c\u5df2\u7ecf\u6253\u4eba\u4eba\u51fa\u4e86\u6c14\uff0c\u8fd8\u5c31\u8981\u4e00\u4e2a\u9053\u6b49\uff0c\u4e0d\u50cf\u6210\u5e74\u4eba\u7684\u601d\u7ef4\u3002 \u2014\u2014 U\u7684\u77ed\u8bc4", "id": "34951002", "title": "\u5e78\u798f\u5230\u4e07\u5bb6", "label": null, "actors": ["\u8d75\u4e3d\u9896", "\u7f57\u664b", "\u5218\u5a01"], "interest": null, "type": "tv", "description": "", "has_linewatch": true, "price": null, "date": null, "info": "\u4e2d\u56fd\u5927\u9646 / \u5267\u60c5 / \u90d1\u6653\u9f99 / \u8d75\u4e3d\u9896 \u7f57\u664b", "url": "https://movie.douban.com/subject/34951002/", "release_date": "06.29", "cover": {"url": "https://img9.doubanio.com/view/photo/m_ratio_poster/public/p2875305149.jpg", "width": 3636, "shape": "rectangle", "height": 5000}, "uri": "douban://douban.com/tv/34951002", "episodes_info": "", "subtype": "", "directors": ["\u90d1\u6653\u9f99"], "reviewer_name": "", "null_rating_reason": ""}, {"original_price": null, "rating": {"count": 211681, "max": 10, "value": 8.6, "star_count": 4.5}, "actions": [], "is_new_tv": false, "year": "2022", "card_subtitle": "2022 / \u4e2d\u56fd\u5927\u9646 / \u5267\u60c5 / \u4e01\u9ed1 \u9c8d\u6210\u5fd7 \u7b26\u7b56\u6b23 / \u5f20\u82e5\u6600 \u767d\u9e7f", "recommend_comment": "\u4e0d\u662f\u56fd\u5185\u6ca1\u597d\u5267\uff0c\u662f\u56fd\u5185\u7684\u6709\u4e9b\u89c2\u4f17\u914d\u4e0d\u4e0a\u597d\u5267\u3002 \u2014\u2014 \ue52b\u7684\u77ed\u8bc4", "id": "35429466", "title": "\u8b66\u5bdf\u8363\u8a89", "label": null, "actors": ["\u5f20\u82e5\u6600", "\u767d\u9e7f", "\u738b\u666f\u6625"], "interest": null, "type": "tv", "description": "", "has_linewatch": true, "price": null, "date": null, "info": "\u4e2d\u56fd\u5927\u9646 / \u5267\u60c5 / \u4e01\u9ed1 / \u5f20\u82e5\u6600 \u767d\u9e7f", "url": "https://movie.douban.com/subject/35429466/", "release_date": "05.28", "cover": {"url": "https://img9.doubanio.com/view/photo/m_ratio_poster/public/p2645165728.jpg", "width": 3333, "shape": "rectangle", "height": 5925}, "uri": "douban://douban.com/tv/35429466", "episodes_info": "", "subtype": "", "directors": ["\u4e01\u9ed1"], "reviewer_name": "", "null_rating_reason": ""}, {"original_price": null, "rating": {"count": 13154, "max": 10, "value": 7.6, "star_count": 4.0}, "actions": [], "is_new_tv": false, "year": "2022", "card_subtitle": "2022 / \u4e2d\u56fd\u5927\u9646 / \u5267\u60c5 \u60ac\u7591 / \u5f20\u6653\u6ce2 / \u6b27\u8c6a \u738b\u781a\u8f89", "recommend_comment": "\u8d85\u9f84\u9ad8\u4e2d\u751f\uff0c\u770b\u7b11\u4e86\u90fd \u2014\u2014 \u829d\u9ebb\u6c64\u5706\u4e0d\u8981\u6c64\u7684\u77ed\u8bc4", "id": "34429670", "title": "\u80c6\u5c0f\u9b3c", "label": null, "actors": ["\u6b27\u8c6a", "\u738b\u781a\u8f89", "\u738b\u7389\u96ef"], "interest": null, "type": "tv", "description": "", "has_linewatch": true, "price": null, "date": null, "info": "\u4e2d\u56fd\u5927\u9646 / \u5267\u60c5 \u60ac\u7591 / \u5f20\u6653\u6ce2 / \u6b27\u8c6a \u738b\u781a\u8f89", "url": "https://movie.douban.com/subject/34429670/", "release_date": "08.08", "cover": {"url": "https://img9.doubanio.com/view/photo/m_ratio_poster/public/p2877651753.jpg", "width": 715, "shape": "rectangle", "height": 1024}, "uri": "douban://douban.com/tv/34429670", "episodes_info": "\u66f4\u65b0\u81f311\u96c6", "subtype": "", "directors": ["\u5f20\u6653\u6ce2"], "reviewer_name": "", "null_rating_reason": ""}, {"original_price": null, "rating": {"count": 4051, "max": 10, "value": 8.5, "star_count": 4.5}, "actions": [], "is_new_tv": false, "year": "2022", "card_subtitle": "2022 / \u7f8e\u56fd / \u559c\u5267 \u72af\u7f6a \u60ac\u7591 / \u7ea6\u7ff0\u00b7\u970d\u592b\u66fc \u7fc1\u83f2\u83f2 / \u53f2\u8482\u592b\u00b7\u9a6c\u4e01 \u9a6c\u4e01\u00b7\u8096\u7279", "recommend_comment": "\u54c8\u54c8\u54c8\u54c8\u7b2c\u4e8c\u5b63\u7684\u6f14\u827a\u884c\u4e1a\u5410\u69fd\u66f4\u4e3a\u7280\u5229\u4e86\u201c\u7b2c\u4e8c\u5b63\u901a\u5e38\u5f88\u7cdf\uff0c\u4e0d\u8fc7\u8fd8\u5728\u6b7b\u4eba\u5c31\u641e\u5457\u201d\u201c\u8fd9\u662fcall back\u201d \u2014\u2014 alty\u7684\u77ed\u8bc4", "id": "35599435", "title": "\u516c\u5bd3\u5927\u697c\u91cc\u7684\u8c0b\u6740\u6848 \u7b2c\u4e8c\u5b63", "label": null, "actors": ["\u53f2\u8482\u592b\u00b7\u9a6c\u4e01", "\u9a6c\u4e01\u00b7\u8096\u7279", "\u8d5b\u7433\u5a1c\u00b7\u6208\u9ea6\u65af"], "interest": null, "type": "tv", "description": "", "has_linewatch": false, "price": null, "date": null, "info": "\u7f8e\u56fd / \u559c\u5267 \u72af\u7f6a \u60ac\u7591 / \u7ea6\u7ff0\u00b7\u970d\u592b\u66fc / \u53f2\u8482\u592b\u00b7\u9a6c\u4e01 \u9a6c\u4e01\u00b7\u8096\u7279", "url": "https://movie.douban.com/subject/35599435/", "release_date": "06.28", "cover": {"url": "https://img9.doubanio.com/view/photo/m_ratio_poster/public/p2873203244.jpg", "width": 1080, "shape": "rectangle", "height": 1350}, "uri": "douban://douban.com/tv/35599435", "episodes_info": "", "subtype": "", "directors": ["\u7ea6\u7ff0\u00b7\u970d\u592b\u66fc"], "reviewer_name": "", "null_rating_reason": ""}, {"original_price": null, "rating": {"count": 35043, "max": 10, "value": 7.7, "star_count": 4.0}, "actions": [], "is_new_tv": false, "year": "2022", "card_subtitle": "2022 / \u4e2d\u56fd\u5927\u9646 / \u52a8\u4f5c \u72af\u7f6a \u60ac\u7591 / \u5f20\u9ece \u9ec4\u4f1f / \u7f57\u664b \u7126\u4fca\u8273", "recommend_comment": "\u4e0a\u6765\u5c31\u6539\u53f0\u8bcd \u8fde\u53e3\u578b\u90fd\u5bf9\u4e0d\u4e0a \u770b\u7740\u4e5f\u592a\u5272\u88c2\u4e86\u5427 \u4e0d\u7528\u8bf4\u53c8\u662f\u8fc7\u4e0d\u4e86\u5ba1\u5457\uff1f \u5efa\u8bae\u4ee5\u540e\u6f14\u5458\u7684\u53f0\u8bcd\u672c\u5148\u63d0\u4ea4\u4e0a\u53bb\u5ba1\u4e00\u904d \u518d\u5f00\u59cb\u62cd \u2014\u2014 \u725b\u7684\u77ed\u8bc4", "id": "35479775", "title": "\u5ead\u5916", "label": null, "actors": ["\u7f57\u664b", "\u7126\u4fca\u8273", "\u590f\u96e8"], "interest": null, "type": "tv", "description": "", "has_linewatch": true, "price": null, "date": null, "info": "\u4e2d\u56fd\u5927\u9646 / \u52a8\u4f5c \u72af\u7f6a \u60ac\u7591 / \u5f20\u9ece / \u7f57\u664b \u7126\u4fca\u8273", "url": "https://movie.douban.com/subject/35479775/", "release_date": "07.14", "cover": {"url": "https://img9.doubanio.com/view/photo/m_ratio_poster/public/p2876125335.jpg", "width": 4429, "shape": "rectangle", "height": 7874}, "uri": "douban://douban.com/tv/35479775", "episodes_info": "21\u96c6\u5168", "subtype": "", "directors": ["\u5f20\u9ece"], "reviewer_name": "", "null_rating_reason": ""}, {"original_price": null, "rating": {"count": 30521, "max": 10, "value": 9.3, "star_count": 4.5}, "actions": [], "is_new_tv": false, "year": "2022", "card_subtitle": "2022 / \u4e2d\u56fd\u5927\u9646 / \u5267\u60c5 / \u96f7\u732e\u79be \u738b\u83c1 / \u6768\u84c9 \u5218\u5955\u541b", "recommend_comment": "\u7b2c\u4e00\u96c6\u542c\u5230\u4e86\u67f3\u666e\uff0c\u633a\u4eb2\u5207\u7684\u3002\u4e00\u90e8\u5357\u65b9\u4eba\u7684\u5267\u7ec8\u4e8e\u4e0d\u518d\u6ee1\u53e3\u513f\u5316\u97f3\n\u5f00\u64ad\u524d\u5149\u770b\u5267\u7167\u90fd\u6ca1\u770b\u51fa\u6765\u662f\u6768\u84c9\ud83d\ude02\n\u524d\u4e24\u96c6\u633a\u611f\u52a8\u7684\n\u6768\u84c9\u628a\u9ec4\u6587\u79c0\u5851\u9020\u5f97\u633a\u597d\u7684\uff0c\u5979\u7684\u5171\u60c5\u80fd\u529b\u5f88\u5f3a\uff0c\u8868\u6f14\u6734\u5b9e\u53c8\u771f\u8bda\u3002\u8fd9\u4e2a\u5267\u4e2d\u95f4\u6709\u62cd\u5f97\u5f88\u4e00\u822c\u7684\u5730\u65b9\uff0c\u4f46\u6ca1\u6709\u72d7\u8840\u5267\u60c5\u548c\u523b\u677f\u8bf4\u6559\uff0c\u5c31\u662f\u5f88\u597d\u7684\u3002\u5230\u6700\u540e\u4e00\u96c6\u6211\u53c8\u54ed\u5f97\u7a00\u91cc\u54d7\u5566\u7684\uff0c\u56e0\u4e3a\u5979\u4e0d\u662f\u4efb\u4f55\u4e00\u4e2a\u7535\u89c6\u5267\u89d2\u8272\uff0c\u662f\u66fe\u7ecf\u6d3b\u751f\u751f\u7684\u4eba\uff0c\u662f\u5728\u770b\u5f00\u5934\u5c31\u77e5\u9053\u7ed3\u5c40\u7684\u4eba\u3002\u592a\u96be\u8fc7\u4e86\u3002 \u2014\u2014 ISABELLA\u7684\u77ed\u8bc4", "id": "35498561", "title": "\u5927\u5c71\u7684\u5973\u513f", "label": null, "actors": ["\u6768\u84c9", "\u5218\u5955\u541b", "\u675c\u6653\u5e06"], "interest": null, "type": "tv", "description": "", "has_linewatch": true, "price": null, "date": null, "info": "\u4e2d\u56fd\u5927\u9646 / \u5267\u60c5 / \u96f7\u732e\u79be / \u6768\u84c9 \u5218\u5955\u541b", "url": "https://movie.douban.com/subject/35498561/", "release_date": "06.26", "cover": {"url": "https://img9.doubanio.com/view/photo/m_ratio_poster/public/p2876483176.jpg", "width": 1080, "shape": "rectangle", "height": 1512}, "uri": "douban://douban.com/tv/35498561", "episodes_info": "", "subtype": "", "directors": ["\u96f7\u732e\u79be"], "reviewer_name": "", "null_rating_reason": ""}]