[{"title": "\u68a6\u9b47\u5e7b\u666f\u5f55", "original_title": "Nightmares and Dreamscapes: From the Stories of Stephen King", "is_tv": true, "year": "2006", "id": "1829040", "poster": "https://img9.doubanio.com/view/photo/s_ratio_poster/public/p2375145120.webp", "rating": {"count": 3113, "max": 10, "star_count": 4.0, "value": 7.6}, "role_desc": "\u7f57\u4f2f\u00b7\u9c8d\u66fc / \u7c73\u51ef\u5c14\u00b7\u8428\u6d1b\u95e8 / \u5a01\u5ec9\u00b7\u8d6b\u7279 / \u5a01\u5ec9\u59c6\u00b7H\u00b7\u6885\u897f / \u827e\u6069\u00b7\u8d1d\u5229 / \u7406\u67e5\u5fb7\u00b7\u6258\u9a6c\u65af"}]