{"_id": {"$oid": "5fb7f16370f0c5debee8c38b"}, "rating": {"count": 1064, "max": 10, "star_count": 3.0, "value": 6.1}, "lineticket_url": "", "gallery_topic_count": 0, "pubdate": ["2006-01-28"], "last_episode_number": null, "pic": {"large": "https://img9.doubanio.com/view/photo/m_ratio_poster/public/p2263263233.webp", "normal": "https://img9.doubanio.com/view/photo/s_ratio_poster/public/p2263263233.webp"}, "vendor_count": 0, "body_bg_color": "f9f6f4", "is_tv": false, "head_info": null, "intro": "\u300a2006\u5e74\u4e2d\u592e\u7535\u89c6\u53f0\u6625\u8282\u8054\u6b22\u665a\u4f1a\u300b\uff08\u7b80\u79f0\uff1a2006\u5e74\u592e\u89c6\u72d7\u5e74\u6625\u665a\uff09\u662f\u7531\u4e2d\u592e\u7535\u89c6\u53f0\u5236\u4f5c\u64ad\u51fa\u7684\u7efc\u827a\u6027\u6587\u827a\u665a\u4f1a\uff0c\u665a\u4f1a\u516d\u4f4d\u4e3b\u6301\u4eba\u662f\u6731\u519b\u3001\u5468\u6d9b\u3001\u674e\u548f\u3001\u8463\u537f\u3001\u5f20\u6cfd\u7fa4\u3001\u5218\u82b3\u83f2\u3002\n\u665a\u4f1a\u4ee5\u201c\u7231\u4e0e\u548c\u8c10\u201d\u4e3a\u4e3b\u9898\u5b9a\u4f4d\uff0c\u835f\u8403\u4e86\u76f8\u58f0\u3001\u5c0f\u54c1\u3001\u821e\u8e48\u3001\u6742\u6280\u3001\u9b54\u672f\u3001\u620f\u66f2\u7b49\u5404\u827a\u672f\u95e8\u7c7b\u7684\u7cbe\u54c1\u8282\u76ee\uff0c\u5728\u4f53\u73b0\u4e2d\u534e\u6c11\u65cf\u4f18\u79c0\u6587\u5316\u4f20\u7edf\u7684\u540c\u65f6\uff0c\u5448\u73b0\u51fa\u4e00\u5e45\u6587\u5316\u591a\u5143\u6027\u7684\u7eda\u4e3d\u753b\u5377\u3002\n\u665a\u4f1a\u4e8e2006\u5e741\u670828\u65e5\u665a20:00\u5728\u4e2d\u592e\u7535\u89c6\u53f0\u7efc\u5408\u9891\u9053\u3001\u4e2d\u6587\u56fd\u9645\u9891\u9053\u7b49\u73b0\u573a\u76f4\u64ad\uff0c\u4e2d\u592e\u4eba\u6c11\u5e7f\u64ad\u7535\u53f0\u540c\u6b65\u76f4\u64ad\u3002", "ticket_price_info": "", "vendor_icons": [], "year": "2006", "card_subtitle": "2006 / \u4e2d\u56fd\u5927\u9646 / \u97f3\u4e50 \u6b4c\u821e / \u90ce\u6606 \u6768\u4e1c\u5347 / \u6731\u519b \u5468\u6d9b", "forum_info": null, "webisode": null, "id": "26593967", "is_restrictive": false, "languages": ["\u6c49\u8bed\u666e\u901a\u8bdd"], "genres": ["\u97f3\u4e50", "\u6b4c\u821e"], "can_interact": true, "review_count": 0, "title": "2006\u5e74\u4e2d\u592e\u7535\u89c6\u53f0\u6625\u8282\u8054\u6b22\u665a\u4f1a", "has_linewatch": false, "ugc_tabs": [{"source": "reviews", "type": "review", "title": "\u5f71\u8bc4"}, {"source": "forum_topics", "type": "forum", "title": "\u8ba8\u8bba"}], "forum_topic_count": 0, "webview_info": {}, "is_released": true, "vendors": [], "actors": [{"name": "\u6731\u519b", "roles": ["\u4e3b\u6301\u4eba", "\u6f14\u5458", "\u5bfc\u6f14"], "title": "\u6731\u519b\uff08\u540c\u540d\uff09\u4e2d\u56fd,\u7518\u8083,\u5170\u5dde\u5f71\u89c6\u6f14\u5458", "url": "https://movie.douban.com/celebrity/1274889/", "abstract": "\u6731\u519b\uff0c\u7537\uff0c1964\u5e74\u51fa\u751f\uff0c\u7956\u7c4d\u6cb3\u5357\u7701\u5b5f\u6d25\u53bf\uff0c\u540e\u968f\u7236\u6bcd\u8fc1\u81f3\u7518\u8083\u7701\u5170\u5dde\u5e02\u3002\u4e2d\u592e\u7535\u89c6\u53f0\u8457\u540d\u4e3b\u6301\u4eba\u3001\u753b\u5bb6\u3001\u4f5c...", "author": null, "uri": "douban://douban.com/celebrity/1274889?subject_id=27495325", "cover_url": "https://img9.doubanio.com/view/celebrity/s_ratio_celebrity/public/p7462.webp", "avatar": {"large": "https://img9.doubanio.com/view/celebrity/s_ratio_celebrity/public/p7462.webp", "normal": "https://img9.doubanio.com/view/celebrity/s_ratio_celebrity/public/p7462.webp"}, "type": "celebrity", "id": "1274889", "sharing_url": "https://www.douban.com/doubanapp/dispatch?uri=/celebrity/1274889/"}, {"name": "\u5468\u6d9b", "roles": ["\u4e3b\u6301\u4eba", "\u6f14\u5458"], "title": "\u5468\u6d9b\uff08\u540c\u540d\uff09\u4e2d\u56fd,\u5b89\u5fbd,\u6dee\u5357\u5f71\u89c6\u6f14\u5458", "url": "https://movie.douban.com/celebrity/1314146/", "abstract": "\u5468\u6d9b\uff0c1968\u5e743\u670823\u65e5\u751f\u4e8e\u5b89\u5fbd\u7701\u6dee\u5357\u5e02\uff0c\u4e2d\u56fd\u4e2d\u592e\u7535\u89c6\u53f0\u8282\u76ee\u4e3b\u6301\u4eba\uff0c\u592e\u89c6\u5927\u578b\u8282\u76ee\u4e2d\u5fc3\u526f\u4e3b\u4efb\uff0c\u5168\u56fd\u9752\u8054\u5e38...", "author": null, "uri": "douban://douban.com/celebrity/1314146?subject_id=27502170", "cover_url": "https://img9.doubanio.com/view/celebrity/s_ratio_celebrity/public/p1527520806.64.webp", "avatar": {"large": "https://img9.doubanio.com/view/celebrity/s_ratio_celebrity/public/p1527520806.64.webp", "normal": "https://img9.doubanio.com/view/celebrity/s_ratio_celebrity/public/p1527520806.64.webp"}, "type": "celebrity", "id": "1314146", "sharing_url": "https://www.douban.com/doubanapp/dispatch?uri=/celebrity/1314146/"}, {"name": "\u674e\u548f", "roles": ["\u4e3b\u6301\u4eba", "\u6f14\u5458", "\u914d\u97f3"], "title": "\u674e\u548f\uff08\u540c\u540d\uff09\u4e2d\u56fd,\u65b0\u7586,\u4e4c\u9c81\u6728\u9f50\u5f71\u89c6\u6f14\u5458", "url": "https://movie.douban.com/celebrity/1334207/", "abstract": "\u674e\u548f\uff081968\u5e745\u67083\u65e5\u81f32018\u5e7410\u670825\u65e5\uff09\uff0c\u51fa\u751f\u4e8e\u65b0\u7586\u4e4c\u9c81\u6728\u9f50\uff0c\u6bd5\u4e1a\u4e8e\u4e2d\u56fd\u4f20\u5a92\u5927\u5b66\uff0c\u4e2d\u56fd\u5185\u5730\u8282\u76ee\u4e3b\u6301\u4eba...", "author": null, "uri": "douban://douban.com/celebrity/1334207?subject_id=27484563", "cover_url": "https://img9.doubanio.com/view/celebrity/s_ratio_celebrity/public/p1524125294.41.webp", "avatar": {"large": "https://img9.doubanio.com/view/celebrity/s_ratio_celebrity/public/p1524125294.41.webp", "normal": "https://img9.doubanio.com/view/celebrity/s_ratio_celebrity/public/p1524125294.41.webp"}, "type": "celebrity", "id": "1334207", "sharing_url": "https://www.douban.com/doubanapp/dispatch?uri=/celebrity/1334207/"}], "interest": null, "episodes_count": 0, "color_scheme": {"is_dark": true, "primary_color_light": "a53412", "_base_color": [0.03878406708595389, 0.8882681564245811, 0.7019607843137254], "secondary_color": "f9f6f4", "_avg_color": [0.04989384288747347, 0.8674033149171271, 0.7098039215686275], "primary_color_dark": "7f280e"}, "type": "movie", "mini_program_name": "gh_c9bfaa84f27b", "null_rating_reason": "", "linewatches": [], "info_url": "https://www.douban.com/doubanapp//h5/movie/26593967/desc", "tags": [{"url": "https://www.douban.com/channel/30168864", "uri": "douban://douban.com/channel/30168864", "id": "30168864", "is_channel": true, "name": "\u6625\u665a"}, {"url": "https://www.douban.com/channel/30168821", "uri": "douban://douban.com/channel/30168821", "id": "30168821", "is_channel": true, "name": "\u56fd\u4ea7\u7535\u5f71"}, {"url": "https://www.douban.com/channel/30169229", "uri": "douban://douban.com/channel/30169229", "id": "30169229", "is_channel": true, "name": "\u97f3\u4e50"}, {"url": "https://www.douban.com/channel/30307500", "uri": "douban://douban.com/channel/30307500", "id": "30307500", "is_channel": true, "name": "\u6b4c\u821e\u7247"}, {"url": "https://www.douban.com/channel/30307938", "uri": "douban://douban.com/channel/30307938", "id": "30307938", "is_channel": true, "name": "2000s"}, {"url": "https://www.douban.com/channel/30168845", "uri": "douban://douban.com/channel/30168845", "id": "30168845", "is_channel": true, "name": "\u6587\u827a\u7247"}], "durations": ["247\u5206\u949f"], "comment_count": 113, "cover": {"description": "", "author": {"loc": {"id": "118159", "name": "\u5357\u4eac", "uid": "nanjing"}, "kind": "user", "name": "StevenSuen\u71da", "reg_time": "2012-01-25 08:47:41", "url": "https://www.douban.com/people/58011713/", "uri": "douban://douban.com/user/58011713", "avatar": "https://img9.doubanio.com/icon/up58011713-8.jpg", "type": "user", "id": "58011713", "uid": "StevenSuen-"}, "url": "https://movie.douban.com/photos/photo/2263263233/", "image": {"large": {"url": "https://img9.doubanio.com/view/photo/l/public/p2263263233.webp", "width": 480, "height": 640, "size": 0}, "raw": null, "small": {"url": "https://img9.doubanio.com/view/photo/s/public/p2263263233.webp", "width": 450, "height": 600, "size": 0}, "is_animated": false, "normal": {"url": "https://img9.doubanio.com/view/photo/m/public/p2263263233.webp", "width": 450, "height": 600, "size": 0}}, "uri": "douban://douban.com/photo/2263263233", "create_time": "2015-08-18 17:47:29", "position": 0, "owner_uri": "douban://douban.com/movie/26593967", "type": "photo", "id": "2263263233", "sharing_url": "https://www.douban.com/doubanapp/dispatch?uri=/photo/2263263233/"}, "cover_url": "https://img9.doubanio.com/view/photo/m_ratio_poster/public/p2263263233.webp", "restrictive_icon_url": "", "header_bg_color": "7f280e", "is_douban_intro": false, "honor_infos": [], "sharing_url": "https://www.douban.com/doubanapp/dispatch/movie/26593967", "wechat_timeline_share": "screenshot", "countries": ["\u4e2d\u56fd\u5927\u9646"], "url": "https://movie.douban.com/subject/26593967/", "release_date": null, "original_title": "", "uri": "douban://douban.com/movie/26593967", "pre_playable_date": null, "mini_program_page": "pages/subject/subject?type=movie&id=26593967", "episodes_info": "", "subtype": "movie", "directors": [{"name": "\u90ce\u6606", "roles": ["\u5bfc\u6f14", "\u7f8e\u672f", "\u5236\u7247\u4eba"], "title": "\u90ce\u6606\uff08\u540c\u540d\uff09\u4e2d\u56fd,\u5317\u4eac\u5f71\u89c6\u6f14\u5458", "url": "https://movie.douban.com/celebrity/1355250/", "abstract": "\u90ce\u6606\uff0c\u4e2d\u592e\u7535\u89c6\u53f0\u9ad8\u7ea7\u7f16\u8f91\uff0c\u4e2d\u592e\u7535\u89c6\u53f0\u7efc\u827a\u9891\u9053\u603b\u76d1 \uff0c\u4e2d\u592e\u7535\u89c6\u53f0\u5927\u578b\u8282\u76ee\u5236\u4f5c\u4e2d\u5fc3\u4e3b\u4efb\uff0c\u535a\u58eb\u5b66\u4f4d\u7814\u7a76\u751f...", "author": null, "uri": "douban://douban.com/celebrity/1355250?subject_id=27557831", "cover_url": "https://img9.doubanio.com/view/celebrity/s_ratio_celebrity/public/p1456840098.05.webp", "avatar": {"large": "https://img9.doubanio.com/view/celebrity/s_ratio_celebrity/public/p1456840098.05.webp", "normal": "https://img9.doubanio.com/view/celebrity/s_ratio_celebrity/public/p1456840098.05.webp"}, "type": "celebrity", "id": "1355250", "sharing_url": "https://www.douban.com/doubanapp/dispatch?uri=/celebrity/1355250/"}, {"name": "\u6768\u4e1c\u5347", "roles": ["\u5bfc\u6f14", "\u5176\u5b83"], "title": "\u6768\u4e1c\u5347\uff08\u540c\u540d\uff09\u5f71\u89c6\u6f14\u5458", "url": "https://movie.douban.com/celebrity/1355230/", "abstract": "\u6768\u4e1c\u5347\uff0c\u4e2d\u592e\u7535\u89c6\u53f0\u5927\u578b\u8282\u76ee\u4e2d\u5fc3\u5236\u7247\u4eba\uff0c\u4e3b\u4efb\u7f16\u8f91\uff0c\u4e2d\u592e\u7535\u89c6\u53f0\u8457\u540d\u8d44\u6df1\u5bfc\u6f14\u3002\u4e3b\u8981\u4f5c\u54c1\u67092000\u5e74\u56fd\u5e86\u4e13\u9898...", "author": null, "uri": "douban://douban.com/celebrity/1355230?subject_id=27557811", "cover_url": "https://img9.doubanio.com/view/celebrity/s_ratio_celebrity/public/p1481725257.84.webp", "avatar": {"large": "https://img9.doubanio.com/view/celebrity/s_ratio_celebrity/public/p1481725257.84.webp", "normal": "https://img9.doubanio.com/view/celebrity/s_ratio_celebrity/public/p1481725257.84.webp"}, "type": "celebrity", "id": "1355230", "sharing_url": "https://www.douban.com/doubanapp/dispatch?uri=/celebrity/1355230/"}], "is_show": false, "in_blacklist": false, "pre_release_desc": "", "video": null, "aka": [], "webisode_count": 0, "trailer": null, "scrap_count": 1}