{"rating": {"count": 179, "max": 10, "star_count": 4.0, "value": 7.6}, "pubdate": ["2017-07-09(\u65e5\u672c)"], "pic": {"large": "https://img9.doubanio.com/view/photo/m_ratio_poster/public/p2519158054.webp", "normal": "https://img9.doubanio.com/view/photo/s_ratio_poster/public/p2519158054.webp"}, "vendor_count": 0, "is_tv": true, "intro": "7\u67089\u65e5\u958b\u59cb\u306eNHK BS\u30d7\u30ec\u30df\u30a2\u30e0\u306e\u30c9\u30e9\u30de\u300e\u5b9a\u5e74\u5973\u5b50\u300f\u8a66\u5199\u4f1a\u304c\u884c\u308f\u308c\u3001\u4e3b\u6f14\u306e\u5357\u679c\u6b69\u3001\u5171\u6f14\u306e\u8349\u5208\u6c11\u4ee3\u3001\u6e05\u6c34\u30df\u30c1\u30b3\u3001\u77f3\u91ce\u771f\u5b50\u306e4\u4eba\u304c\u811a\u672c\u5bb6\u306e\u7530\u6e15\u4e45\u7f8e\u5b50\u6c0f\u3068\u3068\u3082\u306b\u767b\u5834\u3057\u305f\u3002\n\u5357\u304c\u6f14\u3058\u308b\u6df1\u5c71\u9ebb\u5b50\u306f53\u624d\u3002\u5927\u624b\u5546\u793e\u306e\u90e8\u9577\u3092\u52d9\u3081\u3066\u3044\u305f\u304c\u3001\u7a81\u7136\u306e\u914d\u7f6e\u8ee2\u63db\u3092\u547d\u3058\u3089\u308c\u3001\u65b0\u3057\u3044\u8077\u5834\u3067\u306f\u90aa\u9b54\u8005\u6271\u3044\u3092\u3055\u308c\u308b\u3002\u3055\u3089\u306b\u306f\u3001\u7d50\u5a5a\u3057\u305f\u5a18\uff08\u5c71\u4e0b\u30ea\u30aa\uff09\u304c\u5bb6\u306b\u51fa\u623b\u3063\u3066\u304d\u305f\u308a\u3001\u5143\u592b\u306e\u6bcd\u89aa\uff08\u8349\u7b1b\u5149\u5b50\uff09\u306e\u4ecb\u8b77\u3092\u305b\u3056\u308b\u3092\u5f97\u306a\u304f\u306a\u308b\u306a\u3069\u3001\u4e03\u8ee2\u516b\u5012\u306e\u4eba\u751f\u3068\u306a\u308b\u2026\u3002\n\u604b\u30a2\u30ea\u6d99\u30a2\u30ea\u306e\u30cf\u30fc\u30c8\u30a6\u30a9\u30fc\u30df\u30f3\u30b0\u30c9\u30e9\u30de\u3068\u3044\u3046\u30c9\u30e9\u30de\u300e\u5b9a\u5e74\u5973\u5b50\u300f\u3002\u8349\u5208\u3001\u77f3\u91ce\u3001\u6e05\u6c34\u306f\u3044\u305a\u308c\u3082\u9ebb\u5b50\u306e\u53cb\u4eba\u5f79\u3068\u3057\u3066\u51fa\u6f14\u3002\u6bce\u9031\u65e5\u66dc\u3088\u308b10\u6642\u304b\u308910\u664249\u5206\u3067\u3001\u51688\u56de\u3002", "webisode_count": 0, "year": "2017", "card_subtitle": "2017 / \u65e5\u672c / \u585a\u672c\u8fde\u5e73 \u732a\u539f\u8fbe\u4e09 / \u5357\u679c\u6b65 \u5c71\u53e3\u7950\u4e00\u90ce", "id": "27059203", "languages": ["\u65e5\u8bed"], "genres": [], "title": "\u5b9a\u5e74\u5973\u5b50", "is_released": true, "vendors": [], "actors": [{"name": "\u5357\u679c\u6b65", "roles": ["\u6f14\u5458", "\u914d\u97f3"], "title": "\u5357\u679c\u6b65\uff08\u540c\u540d\uff09\u65e5\u672c,\u5175\u5e93\u53bf\u5f71\u89c6\u6f14\u5458", "url": "https://movie.douban.com/celebrity/1005233/", "user": null, "character": "\u6f14\u5458", "uri": "douban://douban.com/celebrity/1005233?subject_id=27210924", "avatar": {"large": "https://img9.doubanio.com/view/celebrity/raw/public/p1510978444.11.jpg", "normal": "https://img9.doubanio.com/view/celebrity/raw/public/p1510978444.11.jpg"}, "sharing_url": "https://www.douban.com/doubanapp/dispatch?uri=/celebrity/1005233/", "type": "celebrity", "id": "1005233", "latin_name": "Kaho Minami"}, {"name": "\u5c71\u53e3\u7950\u4e00\u90ce", "roles": ["\u6f14\u5458"], "title": "\u5c71\u53e3\u7950\u4e00\u90ce\uff08\u540c\u540d\uff09\u65e5\u672c\u9e7f\u5c9b\u53bf\u5f71\u89c6\u6f14\u5458", "url": "https://movie.douban.com/celebrity/1318759/", "user": null, "character": "\u6f14\u5458", "uri": "douban://douban.com/celebrity/1318759?subject_id=27483430", "avatar": {"large": "https://img9.doubanio.com/view/celebrity/raw/public/p1425287630.12.jpg", "normal": "https://img9.doubanio.com/view/celebrity/raw/public/p1425287630.12.jpg"}, "sharing_url": "https://www.douban.com/doubanapp/dispatch?uri=/celebrity/1318759/", "type": "celebrity", "id": "1318759", "latin_name": "Yuichiro Yamaguchi"}, {"name": "\u8349\u5208\u6c11\u4ee3", "roles": ["\u6f14\u5458", "\u914d\u97f3"], "title": "\u8349\u5208\u6c11\u4ee3\uff08\u540c\u540d\uff09\u65e5\u672c,\u4e1c\u4eac\u5f71\u89c6\u6f14\u5458", "url": "https://movie.douban.com/celebrity/1045860/", "user": null, "character": "\u6f14\u5458", "uri": "douban://douban.com/celebrity/1045860?subject_id=27251618", "avatar": {"large": "https://img9.doubanio.com/view/celebrity/raw/public/p26145.jpg", "normal": "https://img9.doubanio.com/view/celebrity/raw/public/p26145.jpg"}, "sharing_url": "https://www.douban.com/doubanapp/dispatch?uri=/celebrity/1045860/", "type": "celebrity", "id": "1045860", "latin_name": "Tamiyo Kusakari"}, {"name": "\u6e05\u6c34\u7f8e\u667a\u5b50", "roles": ["\u6f14\u5458", "\u914d\u97f3"], "title": "\u6e05\u6c34\u7f8e\u667a\u5b50\uff08\u540c\u540d\uff09\u65e5\u672c,\u5c90\u961c\u5f71\u89c6\u6f14\u5458", "url": "https://movie.douban.com/celebrity/1144887/", "user": null, "character": "\u6f14\u5458", "uri": "douban://douban.com/celebrity/1144887?subject_id=27350758", "avatar": {"large": "https://img9.doubanio.com/view/celebrity/raw/public/p38243.jpg", "normal": "https://img9.doubanio.com/view/celebrity/raw/public/p38243.jpg"}, "sharing_url": "https://www.douban.com/doubanapp/dispatch?uri=/celebrity/1144887/", "type": "celebrity", "id": "1144887", "latin_name": "Michiko Shimizu"}, {"name": "\u77f3\u91ce\u771f\u5b50", "roles": ["\u6f14\u5458"], "title": "\u77f3\u91ce\u771f\u5b50\uff08\u540c\u540d\uff09\u65e5\u672c,\u5175\u5e93\u53bf\u5f71\u89c6\u6f14\u5458", "url": "https://movie.douban.com/celebrity/1006028/", "user": null, "character": "\u6f14\u5458", "uri": "douban://douban.com/celebrity/1006028?subject_id=27211719", "avatar": {"large": "https://img9.doubanio.com/view/celebrity/raw/public/p30514.jpg", "normal": "https://img9.doubanio.com/view/celebrity/raw/public/p30514.jpg"}, "sharing_url": "https://www.douban.com/doubanapp/dispatch?uri=/celebrity/1006028/", "type": "celebrity", "id": "1006028", "latin_name": "Mako Ishino"}, {"name": "\u753a\u7530\u542f\u592a", "roles": ["\u6f14\u5458", "\u5bfc\u6f14"], "title": "\u753a\u7530\u542f\u592a\uff08\u540c\u540d\uff09\u65e5\u672c,\u7fa4\u9a6c\u53bf\u5f71\u89c6\u6f14\u5458", "url": "https://movie.douban.com/celebrity/1326403/", "user": null, "character": "\u6f14\u5458", "uri": "douban://douban.com/celebrity/1326403?subject_id=27551074", "avatar": {"large": "https://img9.doubanio.com/view/personage/raw/public/56efd90436ac002b6c05063c4be4191a.jpg", "normal": "https://img9.doubanio.com/view/personage/raw/public/56efd90436ac002b6c05063c4be4191a.jpg"}, "sharing_url": "https://www.douban.com/doubanapp/dispatch?uri=/celebrity/1326403/", "type": "celebrity", "id": "1326403", "latin_name": "Keita Machida"}, {"name": "\u5c71\u4e0b\u8389\u7eea", "roles": ["\u6f14\u5458"], "title": "\u5c71\u4e0b\u8389\u7eea\uff08\u540c\u540d\uff09\u65e5\u672c,\u5fb3\u5c9b\u53bf,\u5fb3\u5c9b\u5e02\u5f71\u89c6\u6f14\u5458", "url": "https://movie.douban.com/celebrity/1275841/", "user": null, "character": "\u6f14\u5458", "uri": "douban://douban.com/celebrity/1275841?subject_id=27494102", "avatar": {"large": "https://img9.doubanio.com/view/personage/raw/public/3bf551c0295e0917f0e8a9d13554a5eb.jpg", "normal": "https://img9.doubanio.com/view/personage/raw/public/3bf551c0295e0917f0e8a9d13554a5eb.jpg"}, "sharing_url": "https://www.douban.com/doubanapp/dispatch?uri=/celebrity/1275841/", "type": "celebrity", "id": "1275841", "latin_name": "Rio Yamashita"}, {"name": "\u9ad8\u91ce\u5fd7\u7a57", "roles": ["\u6f14\u5458"], "title": "\u9ad8\u91ce\u5fd7\u7a57\uff08\u540c\u540d\uff09\u65e5\u672c,\u4e1c\u4eac\u90fd\u5f71\u89c6\u6f14\u5458", "url": "https://movie.douban.com/celebrity/1337180/", "uri": "douban://douban.com/celebrity/1337180?subject_id=27545064", "avatar": {"large": "https://img9.doubanio.com/view/celebrity/raw/public/p1503588588.37.jpg", "normal": "https://img9.doubanio.com/view/celebrity/raw/public/p1503588588.37.jpg"}, "sharing_url": "https://www.douban.com/doubanapp/dispatch?uri=/celebrity/1337180/", "type": "celebrity", "id": "1337180", "latin_name": "Shiho Takano", "movies": [{"id": "27059203", "title": "\u5b9a\u5e74\u5973\u5b50", "original_title": "", "year": "2017", "is_tv": true, "rating": {"count": 179, "max": 10, "star_count": 4.0, "value": 7.6}, "poster": "https://img9.doubanio.com/view/photo/m_ratio_poster/public/p2519158054.webp"}], "_id": {"$oid": "632cfe846210308d964e7e4f"}}, {"name": "\u83ca\u6c60\u6843\u5b50", "roles": ["\u6f14\u5458", "\u914d\u97f3"], "title": "\u83ca\u6c60\u6843\u5b50\uff08\u540c\u540d\uff09\u65e5\u672c,\u4e1c\u4eac\u5f71\u89c6\u6f14\u5458", "url": "https://movie.douban.com/celebrity/1047316/", "uri": "douban://douban.com/celebrity/1047316?subject_id=27253077", "avatar": {"large": "https://img9.doubanio.com/view/personage/raw/public/effaa2a417f2dbf3f5766b347413feb0.jpg", "normal": "https://img9.doubanio.com/view/personage/raw/public/effaa2a417f2dbf3f5766b347413feb0.jpg"}, "sharing_url": "https://www.douban.com/doubanapp/dispatch?uri=/celebrity/1047316/", "type": "celebrity", "id": "1047316", "latin_name": "Momoko Kikuchi", "movies": [{"id": "27059203", "title": "\u5b9a\u5e74\u5973\u5b50", "original_title": "", "year": "2017", "is_tv": true, "rating": {"count": 179, "max": 10, "star_count": 4.0, "value": 7.6}, "poster": "https://img9.doubanio.com/view/photo/m_ratio_poster/public/p2519158054.webp"}], "_id": {"$oid": "632cfe846210308d964e7e50"}}, {"name": "\u85e4\u771f\u5229\u5b50", "roles": ["\u6f14\u5458", "\u914d\u97f3"], "title": "\u85e4\u771f\u5229\u5b50\uff08\u540c\u540d\uff09\u65e5\u672c,\u4e1c\u4eac\u5f71\u89c6\u6f14\u5458", "url": "https://movie.douban.com/celebrity/1022018/", "user": null, "character": "\u6f14\u5458", "uri": "douban://douban.com/celebrity/1022018?subject_id=27227745", "avatar": {"large": "https://img9.doubanio.com/view/celebrity/raw/public/p1491881805.66.jpg", "normal": "https://img9.doubanio.com/view/celebrity/raw/public/p1491881805.66.jpg"}, "sharing_url": "https://www.douban.com/doubanapp/dispatch?uri=/celebrity/1022018/", "type": "celebrity", "id": "1022018", "latin_name": "Mariko Fuji"}, {"name": "\u5bfa\u80c1\u5eb7\u6587", "roles": ["\u6f14\u5458", "\u5bfc\u6f14"], "title": "\u5bfa\u80c1\u5eb7\u6587\uff08\u540c\u540d\uff09\u65e5\u672c\uff0c\u5927\u962a\u5e9c\u583a\u5e02\u5f71\u89c6\u6f14\u5458", "url": "https://movie.douban.com/celebrity/1033952/", "user": null, "character": "\u6f14\u5458", "uri": "douban://douban.com/celebrity/1033952?subject_id=27239697", "avatar": {"large": "https://img9.doubanio.com/view/celebrity/raw/public/p35868.jpg", "normal": "https://img9.doubanio.com/view/celebrity/raw/public/p35868.jpg"}, "sharing_url": "https://www.douban.com/doubanapp/dispatch?uri=/celebrity/1033952/", "type": "celebrity", "id": "1033952", "latin_name": "Yasufumi Terawaki"}, {"name": "\u8349\u7b1b\u5149\u5b50", "roles": ["\u6f14\u5458", "\u914d\u97f3"], "title": "\u8349\u7b1b\u5149\u5b50\uff08\u540c\u540d\uff09\u65e5\u672c,\u6a2a\u6ee8\u5f71\u89c6\u6f14\u5458", "url": "https://movie.douban.com/celebrity/1031254/", "user": null, "character": "\u6f14\u5458", "uri": "douban://douban.com/celebrity/1031254?subject_id=27236995", "avatar": {"large": "https://img9.doubanio.com/view/celebrity/raw/public/p41102.jpg", "normal": "https://img9.doubanio.com/view/celebrity/raw/public/p41102.jpg"}, "sharing_url": "https://www.douban.com/doubanapp/dispatch?uri=/celebrity/1031254/", "type": "celebrity", "id": "1031254", "latin_name": "Mitsuko Kusabue"}, {"name": "\u7ec6\u4e95\u9f13\u592a", "roles": ["\u6f14\u5458"], "title": "\u7ec6\u4e95\u9f13\u592a\uff08\u540c\u540d\uff09\u65e5\u672c,\u795e\u5948\u5ddd\u53bf\u5f71\u89c6\u6f14\u5458", "url": "https://movie.douban.com/celebrity/1444244/", "user": null, "character": "\u6f14\u5458", "uri": "douban://douban.com/celebrity/1444244?subject_id=35202187", "avatar": {"large": "https://img9.doubanio.com/view/celebrity/raw/public/p3KjSyKQtoascel_avatar_uploaded1599564181.8.jpg", "normal": "https://img9.doubanio.com/view/celebrity/raw/public/p3KjSyKQtoascel_avatar_uploaded1599564181.8.jpg"}, "sharing_url": "https://www.douban.com/doubanapp/dispatch?uri=/celebrity/1444244/", "type": "celebrity", "id": "1444244", "latin_name": "Nita Hosoi"}, {"name": "\u68ee\u5c71\u826f\u5b50", "roles": ["\u6f14\u5458", "\u914d\u97f3"], "title": "\u68ee\u5c71\u826f\u5b50\uff08\u540c\u540d\uff09\u65e5\u672c,\u4e1c\u4eac\u5f71\u89c6\u6f14\u5458", "url": "https://movie.douban.com/celebrity/1016345/", "user": null, "character": "\u914d\u97f3", "uri": "douban://douban.com/celebrity/1016345?subject_id=27222068", "avatar": {"large": "https://img9.doubanio.com/view/celebrity/raw/public/p1434255448.87.jpg", "normal": "https://img9.doubanio.com/view/celebrity/raw/public/p1434255448.87.jpg"}, "sharing_url": "https://www.douban.com/doubanapp/dispatch?uri=/celebrity/1016345/", "type": "celebrity", "id": "1016345", "latin_name": "Ryoko Moriyama"}, {"name": "\u5927\u65b9\u6590\u7eb1\u5b50", "roles": ["\u6f14\u5458", "\u914d\u97f3"], "title": "\u5927\u65b9\u6590\u7eb1\u5b50\uff08\u540c\u540d\uff09\u65e5\u672c,\u798f\u5c9b\u53bf\u5f71\u89c6\u6f14\u5458", "url": "https://movie.douban.com/celebrity/1386968/", "user": null, "character": "\u6f14\u5458", "uri": "douban://douban.com/celebrity/1386968?subject_id=27663517", "avatar": {"large": "https://img9.doubanio.com/view/celebrity/raw/public/p1525571286.1.jpg", "normal": "https://img9.doubanio.com/view/celebrity/raw/public/p1525571286.1.jpg"}, "sharing_url": "https://www.douban.com/doubanapp/dispatch?uri=/celebrity/1386968/", "type": "celebrity", "id": "1386968", "latin_name": "Hisako Ohkata"}, {"name": "\u83ca\u5730\u7f8e\u9999", "roles": ["\u914d\u97f3", "\u6f14\u5458"], "title": "\u83ca\u5730\u7f8e\u9999\uff08\u540c\u540d\uff09\u65e5\u672c,\u7426\u7389\u5f71\u89c6\u6f14\u5458", "url": "https://movie.douban.com/celebrity/1038964/", "user": null, "character": "\u6f14\u5458", "uri": "douban://douban.com/celebrity/1038964?subject_id=27244715", "avatar": {"large": "https://img9.doubanio.com/view/celebrity/raw/public/p24278.jpg", "normal": "https://img9.doubanio.com/view/celebrity/raw/public/p24278.jpg"}, "sharing_url": "https://www.douban.com/doubanapp/dispatch?uri=/celebrity/1038964/", "type": "celebrity", "id": "1038964", "latin_name": "Mika Kikuchi"}, {"name": "\u4f50\u85e4\u86fe\u6b21\u90ce", "roles": ["\u6f14\u5458"], "title": "\u4f50\u85e4\u86fe\u6b21\u90ce\uff08\u540c\u540d\uff09\u65e5\u672c,\u5927\u962a\u5f71\u89c6\u6f14\u5458", "url": "https://movie.douban.com/celebrity/1026443/", "user": null, "character": "\u6f14\u5458", "uri": "douban://douban.com/celebrity/1026443?subject_id=27232176", "avatar": {"large": "https://img9.doubanio.com/view/celebrity/raw/public/p39217.jpg", "normal": "https://img9.doubanio.com/view/celebrity/raw/public/p39217.jpg"}, "sharing_url": "https://www.douban.com/doubanapp/dispatch?uri=/celebrity/1026443/", "type": "celebrity", "id": "1026443", "latin_name": "Gajiro Satoh"}, {"name": "\u5357\u91ce\u9633\u5b50", "roles": ["\u6f14\u5458"], "title": "\u5357\u91ce\u9633\u5b50\uff08\u540c\u540d\uff09\u65e5\u672c,\u4f0a\u4e39\u5f71\u89c6\u6f14\u5458", "url": "https://movie.douban.com/celebrity/1011377/", "user": null, "character": "\u6f14\u5458", "uri": "douban://douban.com/celebrity/1011377?subject_id=27217069", "avatar": {"large": "https://img9.doubanio.com/view/celebrity/raw/public/p1551796981.1.jpg", "normal": "https://img9.doubanio.com/view/celebrity/raw/public/p1551796981.1.jpg"}, "sharing_url": "https://www.douban.com/doubanapp/dispatch?uri=/celebrity/1011377/", "type": "celebrity", "id": "1011377", "latin_name": "Y\u00f4ko Minamino"}, {"name": "\u5c0f\u91ce\u4e86", "roles": ["\u6f14\u5458"], "title": "\u5c0f\u91ce\u4e86\uff08\u540c\u540d\uff09\u65e5\u672c,\u4eac\u90fd\u5e9c\u5f71\u89c6\u6f14\u5458", "url": "https://movie.douban.com/celebrity/1381801/", "uri": "douban://douban.com/celebrity/1381801?subject_id=27586346", "avatar": {"large": "https://img9.doubanio.com/view/celebrity/raw/public/p1506483951.3.jpg", "normal": "https://img9.doubanio.com/view/celebrity/raw/public/p1506483951.3.jpg"}, "sharing_url": "https://www.douban.com/doubanapp/dispatch?uri=/celebrity/1381801/", "type": "celebrity", "id": "1381801", "latin_name": "Ryo Ono", "movies": [{"id": "27059203", "title": "\u5b9a\u5e74\u5973\u5b50", "original_title": "", "year": "2017", "is_tv": true, "rating": {"count": 179, "max": 10, "star_count": 4.0, "value": 7.6}, "poster": "https://img9.doubanio.com/view/photo/m_ratio_poster/public/p2519158054.webp"}], "_id": {"$oid": "632cfe856210308d964e7e51"}}, {"name": "\u6cb3\u76f8\u6211\u95fb", "roles": ["\u6f14\u5458", "\u914d\u97f3"], "title": "\u6cb3\u76f8\u6211\u95fb\uff08\u540c\u540d\uff09\u65e5\u672c,\u7426\u7389\u5f71\u89c6\u6f14\u5458", "url": "https://movie.douban.com/celebrity/1199170/", "user": null, "character": "\u6f14\u5458", "uri": "douban://douban.com/celebrity/1199170?subject_id=27405130", "avatar": {"large": "https://img9.doubanio.com/view/celebrity/raw/public/p1455674557.64.jpg", "normal": "https://img9.doubanio.com/view/celebrity/raw/public/p1455674557.64.jpg"}, "sharing_url": "https://www.douban.com/doubanapp/dispatch?uri=/celebrity/1199170/", "type": "celebrity", "id": "1199170", "latin_name": "Gamon Kawai"}, {"name": "\u534a\u6d77\u4e00\u6643", "roles": ["\u6f14\u5458"], "title": "\u534a\u6d77\u4e00\u6643\uff08\u540c\u540d\uff09\u65e5\u672c,\u5bae\u57ce\u770c,\u77f3\u5dfb\u5e02,\u8c9e\u5c71\u5f71\u89c6\u6f14\u5458", "url": "https://movie.douban.com/celebrity/1314510/", "user": null, "character": "\u6f14\u5458", "uri": "douban://douban.com/celebrity/1314510?subject_id=27502096", "avatar": {"large": "https://img9.doubanio.com/view/celebrity/raw/public/p24683.jpg", "normal": "https://img9.doubanio.com/view/celebrity/raw/public/p24683.jpg"}, "sharing_url": "https://www.douban.com/doubanapp/dispatch?uri=/celebrity/1314510/", "type": "celebrity", "id": "1314510", "latin_name": "Kazuaki Hankai"}, {"name": "\u86ed\u5b50\u80fd\u6536", "roles": ["\u6f14\u5458"], "title": "\u86ed\u5b50\u80fd\u6536\uff08\u540c\u540d\uff09\u65e5\u672c\u718a\u672c\u770c\u725b\u6df1\u5e02\uff08\u73fe\u5929\u8349\u5e02\uff09\u5f71\u89c6\u6f14\u5458", "url": "https://movie.douban.com/celebrity/1316199/", "uri": "douban://douban.com/celebrity/1316199?subject_id=27547552", "avatar": {"large": "https://img9.doubanio.com/view/celebrity/raw/public/p35495.jpg", "normal": "https://img9.doubanio.com/view/celebrity/raw/public/p35495.jpg"}, "sharing_url": "https://www.douban.com/doubanapp/dispatch?uri=/celebrity/1316199/", "type": "celebrity", "id": "1316199", "latin_name": "Yoshikazu Ebisu", "movies": [{"id": "27059203", "title": "\u5b9a\u5e74\u5973\u5b50", "original_title": "", "year": "2017", "is_tv": true, "rating": {"count": 179, "max": 10, "star_count": 4.0, "value": 7.6}, "poster": "https://img9.doubanio.com/view/photo/m_ratio_poster/public/p2519158054.webp"}], "_id": {"$oid": "632cfe866210308d964e7e52"}}, {"name": "\u5347\u6bc5", "roles": ["\u6f14\u5458"], "title": "\u5347\u6bc5\uff08\u540c\u540d\uff09\u65e5\u672c,\u4e1c\u4eac\u5f71\u89c6\u6f14\u5458", "url": "https://movie.douban.com/celebrity/1038067/", "user": null, "character": "\u6f14\u5458", "uri": "douban://douban.com/celebrity/1038067?subject_id=27243818", "avatar": {"large": "https://img9.doubanio.com/view/celebrity/raw/public/p30147.jpg", "normal": "https://img9.doubanio.com/view/celebrity/raw/public/p30147.jpg"}, "sharing_url": "https://www.douban.com/doubanapp/dispatch?uri=/celebrity/1038067/", "type": "celebrity", "id": "1038067", "latin_name": "Takeshi Masu"}, {"name": "\u4f50\u6237\u4e95\u8d24\u592a", "roles": ["\u6f14\u5458", "\u914d\u97f3"], "title": "\u4f50\u6237\u4e95\u8d24\u592a\uff08\u540c\u540d\uff09\u65e5\u672c,\u5343\u53f6\u53bf\u5f71\u89c6\u6f14\u5458", "url": "https://movie.douban.com/celebrity/1144228/", "user": null, "character": "\u6f14\u5458", "uri": "douban://douban.com/celebrity/1144228?subject_id=27350098", "avatar": {"large": "https://img9.doubanio.com/view/celebrity/raw/public/p38876.jpg", "normal": "https://img9.doubanio.com/view/celebrity/raw/public/p38876.jpg"}, "sharing_url": "https://www.douban.com/doubanapp/dispatch?uri=/celebrity/1144228/", "type": "celebrity", "id": "1144228", "latin_name": "Kenta Satoi"}, {"name": "\u5fd7\u6c34\u900f\u54c9", "roles": ["\u6f14\u5458"], "title": "\u5fd7\u6c34\u900f\u54c9\uff08\u540c\u540d\uff09\u65e5\u672c\u5f71\u89c6\u6f14\u5458", "url": "https://movie.douban.com/celebrity/1437504/", "user": null, "character": "\u6f14\u5458", "uri": "douban://douban.com/celebrity/1437504?subject_id=35063176", "avatar": {"large": "https://img9.doubanio.com/view/celebrity/raw/public/p1595343046.19.jpg", "normal": "https://img9.doubanio.com/view/celebrity/raw/public/p1595343046.19.jpg"}, "sharing_url": "https://www.douban.com/doubanapp/dispatch?uri=/celebrity/1437504/", "type": "celebrity", "id": "1437504", "latin_name": "Toya Shimizu"}, {"name": "\u4e00\u53cc\u9ebb\u5e0c", "roles": ["\u6f14\u5458"], "title": "\u4e00\u53cc\u9ebb\u5e0c\uff08\u540c\u540d\uff09\u65e5\u672c\uff0c\u77f3\u5ddd\u53bf\u5f71\u89c6\u6f14\u5458", "url": "https://movie.douban.com/celebrity/1379950/", "user": null, "character": "\u9970 \u91ce\u6751\u304b\u3048\u3067", "uri": "douban://douban.com/celebrity/1379950?subject_id=27573195", "avatar": {"large": "https://img9.doubanio.com/view/celebrity/raw/public/pzs36FVlgkqwcel_avatar_uploaded1503592780.73.jpg", "normal": "https://img9.doubanio.com/view/celebrity/raw/public/pzs36FVlgkqwcel_avatar_uploaded1503592780.73.jpg"}, "sharing_url": "https://www.douban.com/doubanapp/dispatch?uri=/celebrity/1379950/", "type": "celebrity", "id": "1379950", "latin_name": "Maki Iss\u00f4"}, {"name": "\u5e03\u65bd\u7ed8\u91cc", "roles": ["\u6f14\u5458"], "title": "\u5e03\u65bd\u7ed8\u91cc\uff08\u540c\u540d\uff09\u65e5\u672c,\u4e1c\u4eac\u5f71\u89c6\u6f14\u5458", "url": "https://movie.douban.com/celebrity/1051850/", "user": null, "character": "\u6f14\u5458", "uri": "douban://douban.com/celebrity/1051850?subject_id=27257614", "avatar": {"large": "https://img9.doubanio.com/view/celebrity/raw/public/p1997.jpg", "normal": "https://img9.doubanio.com/view/celebrity/raw/public/p1997.jpg"}, "sharing_url": "https://www.douban.com/doubanapp/dispatch?uri=/celebrity/1051850/", "type": "celebrity", "id": "1051850", "latin_name": "Eri Fuse"}], "episodes_count": 8, "type": "tv", "null_rating_reason": "", "linewatches": [], "info_url": "https://www.douban.com/doubanapp//h5/movie/27059203/desc", "tags": [], "durations": [], "cover": {"description": "", "author": {"loc": {"id": "118159", "name": "\u5357\u4eac", "uid": "nanjing"}, "kind": "user", "name": "Talent", "url": "https://www.douban.com/people/58011713/", "reg_time": "2012-01-25 08:47:41", "uri": "douban://douban.com/user/58011713", "avatar_side_icon_id": "65", "avatar": "https://img9.doubanio.com/icon/up58011713-15.jpg", "id": "58011713", "type": "user", "avatar_side_icon": "https://img9.doubanio.com/view/files/raw/file-1662088254.png", "uid": "58011713"}, "url": "https://movie.douban.com/photos/photo/2519158054/", "image": {"large": {"url": "https://img9.doubanio.com/view/photo/l/public/p2519158054.webp", "width": 800, "height": 1132, "size": 0}, "raw": null, "small": {"url": "https://img9.doubanio.com/view/photo/s/public/p2519158054.webp", "width": 424, "height": 600, "size": 0}, "normal": {"url": "https://img9.doubanio.com/view/photo/m/public/p2519158054.webp", "width": 424, "height": 600, "size": 0}, "is_animated": false}, "uri": "douban://douban.com/photo/2519158054", "create_time": "2018-04-13 16:52:01", "position": 0, "owner_uri": "douban://douban.com/tv/27059203", "type": "photo", "id": "2519158054", "sharing_url": "https://www.douban.com/doubanapp/dispatch?uri=/photo/2519158054/"}, "cover_url": "https://img9.doubanio.com/view/photo/m_ratio_poster/public/p2519158054.webp", "restrictive_icon_url": "", "header_bg_color": "686b7f", "honor_infos": [], "sharing_url": "https://movie.douban.com/subject/27059203/", "subject_collections": [], "countries": ["\u65e5\u672c"], "url": "https://movie.douban.com/subject/27059203/", "release_date": null, "original_title": "", "uri": "douban://douban.com/tv/27059203", "episodes_info": "", "subtype": "tv", "directors": [{"name": "\u585a\u672c\u8fde\u5e73", "roles": ["\u5bfc\u6f14", "\u7f16\u5267", "\u6f14\u5458"], "title": "\u585a\u672c\u8fde\u5e73\uff08\u540c\u540d\uff09None\u5f71\u89c6\u6f14\u5458", "url": "https://movie.douban.com/celebrity/1359802/", "user": null, "character": "\u5bfc\u6f14", "uri": "douban://douban.com/celebrity/1359802?subject_id=27502583", "avatar": {"large": "https://img9.doubanio.com/view/celebrity/raw/public/p1469532106.25.jpg", "normal": "https://img9.doubanio.com/view/celebrity/raw/public/p1469532106.25.jpg"}, "sharing_url": "https://www.douban.com/doubanapp/dispatch?uri=/celebrity/1359802/", "type": "celebrity", "id": "1359802", "latin_name": "Renpei Tsukamoto"}, {"name": "\u732a\u539f\u8fbe\u4e09", "roles": ["\u5bfc\u6f14"], "title": "\u732a\u539f\u8fbe\u4e09\uff08\u540c\u540d\uff09None\u5f71\u89c6\u6f14\u5458", "url": "https://movie.douban.com/celebrity/1391475/", "uri": "douban://douban.com/celebrity/1391475?subject_id=30194856", "avatar": {"large": "https://img9.doubanio.com/f/movie/63acc16ca6309ef191f0378faf793d1096a3e606/pics/movie/celebrity-default-large.png", "normal": "https://img9.doubanio.com/f/movie/8dd0c794499fe925ae2ae89ee30cd225750457b4/pics/movie/celebrity-default-medium.png"}, "sharing_url": "https://www.douban.com/doubanapp/dispatch?uri=/celebrity/1391475/", "type": "celebrity", "id": "1391475", "latin_name": "Tatsuz\u00f4 Inohara", "movies": [{"id": "27059203", "title": "\u5b9a\u5e74\u5973\u5b50", "original_title": "", "year": "2017", "is_tv": true, "rating": {"count": 179, "max": 10, "star_count": 4.0, "value": 7.6}, "poster": "https://img9.doubanio.com/view/photo/m_ratio_poster/public/p2519158054.webp"}], "_id": {"$oid": "632cfe826210308d964e7e4e"}}], "is_show": false, "in_blacklist": false, "pre_release_desc": "", "video": null, "aka": [], "is_restrictive": false, "trailer": null, "vendor_icons": [], "extra": {"douban_id": "27059203", "imdb_id": "tt7080090", "backdrops": []}, "f_tags": ["2017", "\u65e5\u672c", "\u585a\u672c\u8fde\u5e73", "\u732a\u539f\u8fbe\u4e09", "\u5357\u679c\u6b65", "\u5c71\u53e3\u7950\u4e00\u90ce", "\u8349\u5208\u6c11\u4ee3", "\u6e05\u6c34\u7f8e\u667a\u5b50", "\u77f3\u91ce\u771f\u5b50", "\u753a\u7530\u542f\u592a", "\u5c71\u4e0b\u8389\u7eea", "\u9ad8\u91ce\u5fd7\u7a57", "\u83ca\u6c60\u6843\u5b50", "\u85e4\u771f\u5229\u5b50", "\u5bfa\u80c1\u5eb7\u6587", "\u8349\u7b1b\u5149\u5b50", "\u7ec6\u4e95\u9f13\u592a", "\u68ee\u5c71\u826f\u5b50", "\u5927\u65b9\u6590\u7eb1\u5b50", "\u83ca\u5730\u7f8e\u9999", "\u4f50\u85e4\u86fe\u6b21\u90ce", "\u5357\u91ce\u9633\u5b50", "\u5c0f\u91ce\u4e86", "\u6cb3\u76f8\u6211\u95fb", "\u534a\u6d77\u4e00\u6643", "\u86ed\u5b50\u80fd\u6536", "\u5347\u6bc5", "\u4f50\u6237\u4e95\u8d24\u592a", "\u5fd7\u6c34\u900f\u54c9", "\u4e00\u53cc\u9ebb\u5e0c", "\u5e03\u65bd\u7ed8\u91cc"]}