{"rating": null, "pubdate": ["2019-09-21(\u8d8a\u5357)"], "pic": {"large": "https://img9.doubanio.com/view/photo/m_ratio_poster/public/p2573399699.webp", "normal": "https://img9.doubanio.com/view/photo/s_ratio_poster/public/p2573399699.webp"}, "vendor_count": 0, "is_tv": true, "intro": "\u6e29\u67d4\u751c\u7f8e\u7684\u610f\u5c9a\u63a5\u5230\u5de5\u4f5c\u53bb\u68ee\u6797\u5c0f\u5c4b\u91cc\u7167\u6599\u6027\u683c\u53e4\u602a\u7684\u5b9d\u5c9a\uff0c\u8fd9\u4e2a\u9ad8\u51b7\u813e\u6c14\u53c8\u5dee\u52b2\u7684\u5b9d\u5c9a\u5bf9\u610f\u5c9a\u4e00\u5f00\u59cb\u975e\u5e38\u7684\u62b5\u89e6\uff0c\u4f46\u540e\u6765\u4e24\u4eba\u4e5f\u5728\u65e5\u6e10\u7684\u76f8\u5904\u4e2d\uff0c\u6e10\u751f\u60c5\u612b\u3002\u2014\u2014\u6a58\u91cc\u6a58\u6c14\u8bd1\u5236\u7ec4", "webisode_count": 0, "year": "2019", "card_subtitle": "2019 / \u8d8a\u5357", "id": "34880326", "languages": ["\u8d8a\u5357\u8bed"], "genres": [], "title": "\u68ee\u6797\u5c0f\u5c4b\u91cc\u7684\u7231\u60c5\u6545\u4e8b", "is_released": true, "vendors": [], "actors": [], "episodes_count": 7, "type": "tv", "null_rating_reason": "\u6682\u65e0\u8bc4\u5206", "linewatches": [], "info_url": "https://www.douban.com/doubanapp//h5/movie/34880326/desc", "tags": [], "durations": ["25\u5206\u949f"], "cover": {"description": "", "author": {"loc": {"id": "131645", "name": "Palestine", "uid": "131645"}, "kind": "user", "name": "SoloPancyy", "url": "https://www.douban.com/people/165958422/", "reg_time": "2017-08-26 09:58:13", "uri": "douban://douban.com/user/165958422", "avatar_side_icon_id": "", "avatar": "https://img9.doubanio.com/icon/up165958422-8.jpg", "id": "165958422", "type": "user", "avatar_side_icon": "", "uid": "165958422"}, "url": "https://movie.douban.com/photos/photo/2573399699/", "image": {"large": {"url": "https://img9.doubanio.com/view/photo/l/public/p2573399699.webp", "width": 483, "height": 419, "size": 0}, "raw": null, "small": {"url": "https://img9.doubanio.com/view/photo/s/public/p2573399699.webp", "width": 483, "height": 419, "size": 0}, "normal": {"url": "https://img9.doubanio.com/view/photo/m/public/p2573399699.webp", "width": 483, "height": 419, "size": 0}, "is_animated": false}, "uri": "douban://douban.com/photo/2573399699", "create_time": "2019-11-05 18:33:03", "position": 0, "owner_uri": "douban://douban.com/tv/34880326", "type": "photo", "id": "2573399699", "sharing_url": "https://www.douban.com/doubanapp/dispatch?uri=/photo/2573399699/"}, "cover_url": "https://img9.doubanio.com/view/photo/m_ratio_poster/public/p2573399699.webp", "restrictive_icon_url": "", "header_bg_color": "34414c", "honor_infos": [], "sharing_url": "https://movie.douban.com/subject/34880326/", "subject_collections": [], "countries": ["\u8d8a\u5357"], "url": "https://movie.douban.com/subject/34880326/", "release_date": null, "original_title": "M\u00d9A THU \u1ede NG\u00d4I NH\u00c0 TRONG R\u1eeaNG", "uri": "douban://douban.com/tv/34880326", "episodes_info": "", "subtype": "tv", "directors": [], "is_show": false, "in_blacklist": false, "pre_release_desc": "", "video": null, "aka": [], "is_restrictive": false, "trailer": null, "vendor_icons": [], "f_tags": ["2019", "\u8d8a\u5357"]}